pwm_gen.v
module pwm_gen (
    input clk,
    input rst_n,
    input pwm_en,
    input [15:0] period,
    input [7:0]  functions,
    input [15:0] compare1,
    input [15:0] compare2,
    input [15:0] count_val,
    output pwm_out
);
    reg pwm_out_r;
    assign pwm_out = pwm_out_r;

    always @(posedge clk or negedge rst_n) begin
        if (!rst_n)
            pwm_out_r <= 1'b0;
        else if (!pwm_en)
            pwm_out_r <= 1'b0;
        else begin
            if ((compare1 == 0) || (compare1 == compare2))
                pwm_out_r <= 1'b0;
            else begin
                case (functions[1:0])
                    // LEFT aligned – neschimbat
                    2'b00: pwm_out_r <= (count_val <= compare1);

                    // RIGHT aligned – MODIFICAT
                    // Activ dacă valoarea curentă este mai mare sau egală cu pragul
                    2'b01: pwm_out_r <= (count_val >= compare1);

                    // RANGE between – neschimbat
                    2'b10: pwm_out_r <=
                        (count_val >= compare1) && (count_val < compare2);

                    default: pwm_out_r <= 1'b0;
                endcase
            end
        end
    end
endmodule

counter.v
module counter (
    // peripheral clock signals
    input clk,
    input rst_n,
    // register facing signals
    output [15:0] count_val,
    input  [15:0] period,
    input en,
    input count_reset,
    input upnotdown,
    input [7:0] prescale
);

    // ---------------------------
    // Registre interne
    // ---------------------------
    reg [15:0] count_val_r;
    reg [7:0]  prescale_cnt;
    assign count_val = count_val_r;

    // ---------------------------
    // Logică principală
    // ---------------------------
    always @(posedge clk or negedge rst_n) begin
        if (!rst_n) begin
            count_val_r  <= 16'd0;
            prescale_cnt <= 8'd0;

        end else begin

            if (count_reset) begin
                count_val_r  <= 16'd0;
                prescale_cnt <= 8'd0;

            end else if (en) begin

                if (prescale_cnt == prescale) begin
                    prescale_cnt <= 8'd0;

                    if (upnotdown) begin
                        // UP → numără 0 ... period (inclusive)
                        // Modificare: Reset doar cand EGAL cu period
                        if (count_val_r == period) 
                            count_val_r <= 16'd0;
                        else
                            count_val_r <= count_val_r + 1'b1;

                    end else begin
                        // DOWN → numără period ... 0
                        if (count_val_r == 0)
                            count_val_r <= period;
                        else
                            count_val_r <= count_val_r - 1'b1;
                    end

                end else begin
                    prescale_cnt <= prescale_cnt + 1'b1;
                end
            end
        end
    end

endmodule

regs.v
module regs (
    // peripheral clock signals
    input clk,
    input rst_n,
    // decoder facing signals
    input read,
    input write,
    input [5:0] addr,
    output [7:0] data_read,
    input  [7:0] data_write,
    // counter programming signals
    input  [15:0] counter_val,
    output [15:0] period,
    output en,
    output count_reset,
    output upnotdown,
    output [7:0] prescale,
    // PWM signal programming values
    output pwm_en,
    output [7:0] functions,
    output [15:0] compare1,
    output [15:0] compare2
);

    // -----------------------------
    // Registre interne
    // -----------------------------
    reg [15:0] r_period;
    reg        r_en;
    reg        r_count_reset;
    reg        r_upnotdown;
    reg [7:0]  r_prescale;
    reg        r_pwm_en;
    reg [7:0]  r_functions;
    reg [15:0] r_compare1;
    reg [15:0] r_compare2;
    reg [7:0]  r_data_read;

    // -----------------------------
    // Conectări către ieșiri
    // -----------------------------
    assign period     = r_period;
    assign en         = r_en;
    assign count_reset = r_count_reset;
    assign upnotdown  = r_upnotdown;
    assign prescale   = r_prescale;
    assign pwm_en     = r_pwm_en;
    assign functions  = r_functions;
    assign compare1   = r_compare1;
    assign compare2   = r_compare2;
    assign data_read  = r_data_read;

    // -----------------------------
    // LOGICA DE SCRIERE
    // -----------------------------
    always @(posedge clk or negedge rst_n) begin
        if (!rst_n) begin
            r_period      <= 16'h0000;
            r_en          <= 1'b0;
            r_count_reset <= 1'b0;
            r_upnotdown   <= 1'b0;
            r_prescale    <= 8'h00;
            r_pwm_en      <= 1'b0;
            r_functions   <= 8'h00;
            r_compare1    <= 16'h0000;
            r_compare2    <= 16'h0000;
        end else begin
            r_count_reset <= 1'b0; // puls de un ciclu

            if (write) begin
                case (addr)
                    6'h00: r_period[7:0]   <= data_write;
                    6'h01: r_period[15:8]  <= data_write;
                    6'h02: r_en            <= data_write[0];
                    6'h03: r_compare1[7:0] <= data_write;
                    6'h04: r_compare1[15:8] <= data_write;
                    6'h05: r_compare2[7:0] <= data_write;
                    6'h06: r_compare2[15:8] <= data_write;
                    6'h07: r_count_reset   <= 1'b1; // write-only
                    6'h0A: r_prescale      <= data_write;
                    6'h0B: r_upnotdown     <= data_write[0];
                    6'h0C: r_pwm_en        <= data_write[0];
                    6'h0D: r_functions     <= data_write;
                endcase
            end
        end
    end

    // -----------------------------
    // LOGICA DE CITIRE
    // -----------------------------
    always @(*) begin
        if (!read) begin
            r_data_read = 8'h00;
        end else begin
            case (addr)
                6'h00: r_data_read = r_period[7:0];
                6'h01: r_data_read = r_period[15:8];
                6'h02: r_data_read = {7'd0, r_en};
                6'h03: r_data_read = r_compare1[7:0];
                6'h04: r_data_read = r_compare1[15:8];
                6'h05: r_data_read = r_compare2[7:0];
                6'h06: r_data_read = r_compare2[15:8];
                6'h07: r_data_read = 8'h00; // write-only
                6'h08: r_data_read = counter_val[7:0];
                6'h09: r_data_read = counter_val[15:8];
                6'h0A: r_data_read = r_prescale;
                6'h0B: r_data_read = {7'd0, r_upnotdown};
                6'h0C: r_data_read = {7'd0, r_pwm_en};
                6'h0D: r_data_read = r_functions;
                default: r_data_read = 8'h00;
            endcase
        end
    end

endmodule

instr_dcd.v
module instr_dcd (
    // peripheral clock signals
    input clk,
    input rst_n,
    // towards SPI slave interface signals
    input byte_sync,
    input [7:0] data_in,
    output [7:0] data_out,
    // register access signals
    output read,
    output write,
    output [5:0] addr,
    input  [7:0] data_read,
    output [7:0] data_write
);

    // ieșiri ca wire, conduse din registre interne
    reg        read_r, write_r;
    reg [5:0]  addr_r;
    reg [7:0]  data_out_r, data_write_r;

    assign read       = read_r;
    assign write      = write_r;
    assign addr       = addr_r;
    assign data_out   = data_out_r;
    assign data_write = data_write_r;

    // FSM
    localparam S_CMD  = 1'b0;
    localparam S_DATA = 1'b1;

    reg state;
    reg rw_bit;  // 1=write, 0=read (latched din command byte)

    always @(posedge clk or negedge rst_n) begin
        if (!rst_n) begin
            state        <= S_CMD;
            rw_bit       <= 1'b0;
            addr_r       <= 6'd0;
            data_out_r   <= 8'd0;
            data_write_r <= 8'd0;
            read_r       <= 1'b0;
            write_r      <= 1'b0;

        end else begin
            // pulse de 1 ciclu
            read_r  <= 1'b0;
            write_r <= 1'b0;

            if (byte_sync) begin
                case (state)
                    // Primul byte: command
                    S_CMD: begin
                        rw_bit <= data_in[7];          // CORE SPOT: latchează RW din command
                        addr_r <= data_in[5:0];        // ignoră high/low; adresa e directă
                        state  <= S_DATA;
                    end

                    // Al doilea byte: data
                    S_DATA: begin
                        if (rw_bit) begin
                            // WRITE
                            data_write_r <= data_in;
                            write_r      <= 1'b1;
                        end else begin
                            // READ
                            data_out_r <= data_read;
                            read_r     <= 1'b1;
                        end
                        state <= S_CMD;
                    end
                endcase
            end
        end
    end

endmodule

spi_bridge.v
module spi_bridge (
    // peripheral clock signals
    input clk,
    input rst_n,
    // SPI master facing signals
    input sclk,
    input cs_n,
    input mosi,   // master out slave in
    output miso,  // master in slave out
    // internal facing signals
    output byte_sync,        // pulse = un nou byte primit
    output [7:0] data_in,    // ultimul byte primit
    input  [7:0] data_out    // byte-ul care va fi trimis următor
);

    //----------------------------------------------------------
    //  REGISTRE INTERNE
    //----------------------------------------------------------
    reg [7:0] shift_reg;    // buffer pentru MOSI
    reg [2:0] bit_cnt;      // numără biții 0..7
    reg [7:0] r_data_in;    // primul byte complet
    reg r_miso;             // linia de ieșire către master
    reg r_byte_sync;        // puls sincron cu clk
    reg byte_ready;         // puls nativ (pe domeniul sclk)

    //----------------------------------------------------------
    //  INPUT MOSI — domeniul SPI (pe SCLK)
    //----------------------------------------------------------
    always @(posedge sclk or posedge cs_n or negedge rst_n) begin
        if (!rst_n) begin
            // Reset complet doar la power-on
            bit_cnt    <= 3'd0;
            shift_reg  <= 8'd0;
            byte_ready <= 1'b0;
        end else if (cs_n) begin
            // Cand CS_N e inactiv, resetam DOAR contorul si flag-ul,
            // DAR PASTRAM DATELE in shift_reg pentru a fi citite.
            bit_cnt    <= 3'd0;
            byte_ready <= 1'b0;
            // shift_reg ramane neschimbat
        end else begin
            // ciclul de citire pe frontul crescător SCLK
            shift_reg  <= {shift_reg[6:0], mosi};
            bit_cnt    <= bit_cnt + 3'd1;

            // după 8 biți → semnal „byte ready”
            if (bit_cnt == 3'd7)
                byte_ready <= 1'b1;
            else
                byte_ready <= 1'b0;
        end
    end

    //----------------------------------------------------------
    //  OUTPUT MISO — domeniul SPI (pe SCLK descrescător)
    //----------------------------------------------------------
    // Trimitere MSB first, sincron înapoi spre master
    //----------------------------------------------------------
    always @(negedge sclk or posedge cs_n or negedge rst_n) begin
        if (!rst_n || cs_n)
            r_miso <= 1'b0;
        else
            r_miso <= data_out[7 - bit_cnt];
    end

    //----------------------------------------------------------
    //  SINCRONIZARE CU CEASUL PERIFERIC (clk)
    //----------------------------------------------------------
    // „byte_ready” se întâmplă pe domeniul sclk,
    // deci trebuie adus ca puls în domeniul clk.
    //----------------------------------------------------------
    always @(posedge clk or negedge rst_n) begin
        if (!rst_n) begin
            r_byte_sync <= 1'b0;
            r_data_in   <= 8'd0;
        end else begin
            r_byte_sync <= byte_ready;       // puls de 1 clk
            if (byte_ready)
                r_data_in <= shift_reg;
        end
    end

    //----------------------------------------------------------
    //  CONECTAREA LA IEȘIRI
    //----------------------------------------------------------
    assign byte_sync = r_byte_sync;
    assign data_in   = r_data_in;
    assign miso      = r_miso;

endmodule

top.v
/*
    This file may now be modified as needed for compatibility.
*/

module top(
    // peripheral clock signals
    input clk,
    input rst_n,
    // SPI master facing signals
    input sclk,
    input cs_n,
    input miso,    // TB → DUT
    output mosi,   // DUT → TB
    // peripheral signals
    output pwm_out
);

// SPI / decoder interface signals
wire byte_sync;
wire [7:0] data_in;
wire [7:0] data_out;
wire read;
wire write;
wire [5:0] addr;
wire [7:0] data_read;
wire [7:0] data_write;

// counter / timer signals
wire [15:0] counter_val;
wire [15:0] period;
wire en;
wire count_reset;
wire upnotdown;
wire [7:0] prescale;

// PWM signals
wire pwm_en;
wire [7:0] functions;
wire [15:0] compare1;
wire [15:0] compare2;

// -------------------------------------------------
// SPI BRIDGE
// -------------------------------------------------
// MUST match skeleton: mosi = input, miso = output
spi_bridge i_spi_bridge (
    .clk(clk),
    .rst_n(rst_n),
    .sclk(sclk),
    .cs_n(cs_n),

    // SPI connections FIXED
    .mosi(miso),   // TB MOSI -> SPI input
    .miso(mosi),   // SPI output -> TB MISO

    .byte_sync(byte_sync),
    .data_in(data_in),
    .data_out(data_out)
);
// -------------------------------------------------
// DECODER
// -------------------------------------------------
instr_dcd i_instr_dcd (
    .clk(clk),
    .rst_n(rst_n),
    .byte_sync(byte_sync),
    .data_in(data_in),
    .data_out(data_out),
    .read(read),
    .write(write),
    .addr(addr),
    .data_read(data_read),
    .data_write(data_write)
);

// -------------------------------------------------
// REGISTERS
// -------------------------------------------------
regs i_regs (
    .clk(clk),
    .rst_n(rst_n),
    .read(read),
    .write(write),
    .addr(addr),
    .data_read(data_read),
    .data_write(data_write),
    .counter_val(counter_val),
    .period(period),
    .en(en),
    .count_reset(count_reset),
    .upnotdown(upnotdown),
    .prescale(prescale),
    .pwm_en(pwm_en),
    .functions(functions),
    .compare1(compare1),
    .compare2(compare2)
);

// -------------------------------------------------
// COUNTER
// -------------------------------------------------
counter i_counter (
    .clk(clk),
    .rst_n(rst_n),
    .count_val(counter_val),
    .period(period),
    .en(en),
    .count_reset(count_reset),
    .upnotdown(upnotdown),
    .prescale(prescale)
);

// -------------------------------------------------
// PWM GENERATOR
// -------------------------------------------------
pwm_gen i_pwm_gen (
    .clk(clk),
    .rst_n(rst_n),
    .pwm_en(pwm_en),
    .period(period),
    .functions(functions),
    .compare1(compare1),
    .compare2(compare2),
    .count_val(counter_val),
    .pwm_out(pwm_out)
);

endmodule

tb_top.v
`default_nettype none
`timescale 1ns/1ns

module tb_top_system;

    reg  clk;         
    reg  rst_n;

    reg  tb_mosi;   
    wire tb_miso;    
    reg  sclk;      
    reg  cs_n;       

    wire pwm_out;

    reg[7:0] counter_lsb;

    top dut (
        .clk    (clk),
        .rst_n  (rst_n),
        .sclk   (sclk),
        .cs_n   (cs_n),
        .miso   (tb_mosi),
        .mosi   (tb_miso),
        .pwm_out(pwm_out)
    );

    localparam CLK_HALF   = 50;  
    localparam SCLK_HALF  = 50;   

    localparam [5:0] REG_PERIOD        = 6'h00;
    localparam [5:0] REG_COUNTER_EN    = 6'h02;
    localparam [5:0] REG_COMPARE1      = 6'h03;
    localparam [5:0] REG_COMPARE2      = 6'h05;
    localparam [5:0] REG_COUNTER_RESET = 6'h07;
    localparam [5:0] REG_COUNTER_VAL   = 6'h08;
    localparam [5:0] REG_PRESCALE      = 6'h0A;
    localparam [5:0] REG_UPNOTDOWN     = 6'h0B;
    localparam [5:0] REG_PWM_EN        = 6'h0C;
    localparam [5:0] REG_FUNCTIONS     = 6'h0D;

    localparam [1:0] FUNCTION_ALIGN_LEFT             = 2'b00;
    localparam [1:0] FUNCTION_ALIGN_RIGHT            = 2'b01;
    localparam [1:0] FUNCTION_RANGE_BETWEEN_COMPARES = 2'b10;

    initial begin
        clk = 1'b0;
        forever #(CLK_HALF) clk = ~clk;
    end

    initial begin
  $dumpfile("waves.vcd");
  $dumpvars(0, tb_top_system);
  
  // -------------- DE URMĂRIT -----------------
  // registrele interne și semnale cheie
  $dumpvars(0, tb_top_system.dut.i_regs.r_period);
  $dumpvars(0, tb_top_system.dut.i_regs.r_compare1);
  $dumpvars(0, tb_top_system.dut.i_regs.r_en);
  $dumpvars(0, tb_top_system.dut.i_regs.r_pwm_en);
  $dumpvars(0, tb_top_system.dut.i_regs.r_functions);
  $dumpvars(0, tb_top_system.dut.i_regs.r_prescale);
  $dumpvars(0, tb_top_system.dut.i_counter.count_val_r);
  $dumpvars(0, tb_top_system.dut.i_counter.prescale_cnt);
  $dumpvars(0, tb_top_system.dut.i_pwm_gen.pwm_out_r);
end

    task apply_reset;
        begin
            rst_n  = 1'b0;
            cs_n   = 1'b1;
            sclk   = 1'b0;
            tb_mosi = 1'b0;
            #(10*CLK_HALF); 
            rst_n  = 1'b1;
            #(5*CLK_HALF);
            $display("Time %0t: Reset deasserted.", $time);
        end
    endtask

    task spi_transfer_byte;
        input  [7:0] tx;
        output [7:0] rx;
        integer i;
        begin
            rx = 8'h00;
            for (i = 7; i >= 0; i = i - 1) begin
                tb_mosi = tx[i];
                #(SCLK_HALF);
                sclk = 1'b1;           
                #(SCLK_HALF/2);
                rx[i] = tb_miso;      
                #(SCLK_HALF/2);
                sclk = 1'b0;
            end
        end
    endtask

    task spi_write_reg;
        input  [5:0] addr;
        input  [7:0] data;
        reg    [7:0] cmd;
        reg    [7:0] dummy;
        begin
            cmd = {1'b1, 1'b1, addr};   
            #(SCLK_HALF);
            cs_n = 1'b0;

            spi_transfer_byte(cmd, dummy);
            spi_transfer_byte(data, dummy);

            #(SCLK_HALF);
            cs_n = 1'b1;

            $display("Time %0t: SPI WRITE  addr=0x%02h  data=0x%02h", $time, addr, data);
            #(4*CLK_HALF); 
        end
    endtask

    task spi_read_reg;
        input  [5:0] addr;
        output [7:0] data;
        reg    [7:0] cmd;
        reg    [7:0] rx;
        begin
            cmd = {1'b0, 1'b1, addr};   
            #(SCLK_HALF);
            cs_n = 1'b0;

            spi_transfer_byte(cmd, rx);           
            spi_transfer_byte(8'h00, data);     

            #(SCLK_HALF);
            cs_n = 1'b1;

            $display("Time %0t: SPI READ   addr=0x%02h  data=0x%02h", $time, addr, data);
            #(4*CLK_HALF);
        end
    endtask

    task check_pwm_duty;
        input integer period_val;
        input integer high_per_period;
        input integer num_periods;
        integer total_ticks;
        integer high_count;
        integer i;
        integer exp;
        begin
            total_ticks = (period_val + 1) * num_periods;
            exp         = high_per_period * num_periods;
            high_count  = 0;

            #(5*CLK_HALF);

            for (i = 0; i < total_ticks; i = i + 1) begin
                @(posedge clk);
                if (pwm_out)
                    high_count = high_count + 1;
            end

            if ((high_count >= exp-1) && (high_count <= exp+1)) begin
                $display("[PASS] PWM duty aprox. corect: high=%0d, expected ~%0d", 
                         high_count, exp);
            end else begin
                $display("[FAIL] PWM duty incorect: high=%0d, expected %0d", 
                         high_count, exp);
            end
        end
    endtask

    initial begin
        $display("--- Starting Testbench ---");

        rst_n   = 1'b0;
        cs_n    = 1'b1;
        sclk    = 1'b0;
        tb_mosi = 1'b0;

        apply_reset();

        spi_write_reg(REG_PERIOD,       8'd7);
        spi_write_reg(REG_PRESCALE,     8'd0);
        spi_write_reg(REG_COMPARE1,     8'd3);
        spi_write_reg(REG_COUNTER_EN,   8'd1);
        spi_write_reg(REG_PWM_EN,       8'd1);
        spi_write_reg(REG_FUNCTIONS,    {6'b0, FUNCTION_ALIGN_LEFT});

        spi_write_reg(REG_COUNTER_RESET, 8'd1);
        spi_write_reg(REG_COUNTER_RESET, 8'd0);

        $display("\n--- Test 1: PWM ALIGN_LEFT, compare1=3, period=7 ---");
        check_pwm_duty(7, 4, 5); 


        spi_read_reg(REG_COUNTER_VAL, counter_lsb);

        $display("\n--- Test 2: PWM RANGE_BETWEEN_COMPARES, c1=2, c2=6 ---");
        spi_write_reg(REG_COMPARE1, 8'd2);
        spi_write_reg(REG_COMPARE2, 8'd6);
        spi_write_reg(REG_FUNCTIONS, {6'b0, FUNCTION_RANGE_BETWEEN_COMPARES});

        check_pwm_duty(7, 4, 5); 

        $display("\n--- Test 3: PWM ALIGN_RIGHT, compare1=5 ---");
        spi_write_reg(REG_COMPARE1, 8'd5);
        spi_write_reg(REG_FUNCTIONS, {6'b0, FUNCTION_ALIGN_RIGHT});

        check_pwm_duty(7, 3, 5); 

        $display("\n--- Test 4: PWM UNALIGNED EDGE CASE EQUAL COMPARES ---");
        spi_write_reg(REG_COUNTER_EN, 8'h00);
        spi_write_reg(REG_COMPARE1, 8'h05);
        spi_write_reg(REG_COMPARE2, 8'h05);
        spi_write_reg(REG_COUNTER_EN, 8'h01);
        check_pwm_duty(7, 0, 2);
        
        $display("\n--- Test 5: PWM NOT TRIGGER AT START, compare1=0 ---");
        spi_write_reg(REG_COUNTER_EN, 8'h00);
        spi_write_reg(REG_COMPARE1, 8'h00);
        spi_write_reg(REG_FUNCTIONS, 8'h00);
        spi_write_reg(REG_COUNTER_EN, 8'h01);
        check_pwm_duty(7, 0, 3);

        $display("\n--- Finished Testbench ---");
        $finish;
    end

endmodule

`default_nettype wire

waves.vcd
$date
	Sun Dec 14 16:27:34 2025
$end
$version
	Icarus Verilog
$end
$timescale
	1ns
$end
$scope module tb_top_system $end
$var wire 1 ! tb_miso $end
$var wire 1 " pwm_out $end
$var parameter 32 # CLK_HALF $end
$var parameter 2 $ FUNCTION_ALIGN_LEFT $end
$var parameter 2 % FUNCTION_ALIGN_RIGHT $end
$var parameter 2 & FUNCTION_RANGE_BETWEEN_COMPARES $end
$var parameter 6 ' REG_COMPARE1 $end
$var parameter 6 ( REG_COMPARE2 $end
$var parameter 6 ) REG_COUNTER_EN $end
$var parameter 6 * REG_COUNTER_RESET $end
$var parameter 6 + REG_COUNTER_VAL $end
$var parameter 6 , REG_FUNCTIONS $end
$var parameter 6 - REG_PERIOD $end
$var parameter 6 . REG_PRESCALE $end
$var parameter 6 / REG_PWM_EN $end
$var parameter 6 0 REG_UPNOTDOWN $end
$var parameter 32 1 SCLK_HALF $end
$var reg 1 2 clk $end
$var reg 8 3 counter_lsb [7:0] $end
$var reg 1 4 cs_n $end
$var reg 1 5 rst_n $end
$var reg 1 6 sclk $end
$var reg 1 7 tb_mosi $end
$scope module dut $end
$var wire 1 2 clk $end
$var wire 1 4 cs_n $end
$var wire 1 7 miso $end
$var wire 1 5 rst_n $end
$var wire 1 6 sclk $end
$var wire 1 8 write $end
$var wire 1 9 upnotdown $end
$var wire 1 : read $end
$var wire 1 " pwm_out $end
$var wire 1 ; pwm_en $end
$var wire 8 < prescale [7:0] $end
$var wire 16 = period [15:0] $end
$var wire 1 ! mosi $end
$var wire 8 > functions [7:0] $end
$var wire 1 ? en $end
$var wire 8 @ data_write [7:0] $end
$var wire 8 A data_read [7:0] $end
$var wire 8 B data_out [7:0] $end
$var wire 8 C data_in [7:0] $end
$var wire 16 D counter_val [15:0] $end
$var wire 1 E count_reset $end
$var wire 16 F compare2 [15:0] $end
$var wire 16 G compare1 [15:0] $end
$var wire 1 H byte_sync $end
$var wire 6 I addr [5:0] $end
$scope module i_counter $end
$var wire 1 2 clk $end
$var wire 16 J count_val [15:0] $end
$var wire 1 5 rst_n $end
$var wire 1 9 upnotdown $end
$var wire 8 K prescale [7:0] $end
$var wire 16 L period [15:0] $end
$var wire 1 ? en $end
$var wire 1 E count_reset $end
$var reg 16 M count_val_r [15:0] $end
$var reg 8 N prescale_cnt [7:0] $end
$upscope $end
$scope module i_instr_dcd $end
$var wire 6 O addr [5:0] $end
$var wire 1 2 clk $end
$var wire 8 P data_out [7:0] $end
$var wire 8 Q data_write [7:0] $end
$var wire 1 : read $end
$var wire 1 5 rst_n $end
$var wire 1 8 write $end
$var wire 8 R data_read [7:0] $end
$var wire 8 S data_in [7:0] $end
$var wire 1 H byte_sync $end
$var parameter 1 T S_CMD $end
$var parameter 1 U S_DATA $end
$var reg 6 V addr_r [5:0] $end
$var reg 8 W data_out_r [7:0] $end
$var reg 8 X data_write_r [7:0] $end
$var reg 1 Y read_r $end
$var reg 1 Z rw_bit $end
$var reg 1 [ state $end
$var reg 1 \ write_r $end
$upscope $end
$scope module i_pwm_gen $end
$var wire 1 2 clk $end
$var wire 16 ] count_val [15:0] $end
$var wire 1 " pwm_out $end
$var wire 1 5 rst_n $end
$var wire 1 ; pwm_en $end
$var wire 16 ^ period [15:0] $end
$var wire 8 _ functions [7:0] $end
$var wire 16 ` compare2 [15:0] $end
$var wire 16 a compare1 [15:0] $end
$var reg 1 b pwm_out_r $end
$upscope $end
$scope module i_regs $end
$var wire 6 c addr [5:0] $end
$var wire 1 2 clk $end
$var wire 16 d compare1 [15:0] $end
$var wire 16 e compare2 [15:0] $end
$var wire 1 E count_reset $end
$var wire 16 f counter_val [15:0] $end
$var wire 8 g data_read [7:0] $end
$var wire 8 h data_write [7:0] $end
$var wire 1 ? en $end
$var wire 8 i functions [7:0] $end
$var wire 16 j period [15:0] $end
$var wire 8 k prescale [7:0] $end
$var wire 1 ; pwm_en $end
$var wire 1 : read $end
$var wire 1 5 rst_n $end
$var wire 1 9 upnotdown $end
$var wire 1 8 write $end
$var reg 16 l r_compare1 [15:0] $end
$var reg 16 m r_compare2 [15:0] $end
$var reg 1 n r_count_reset $end
$var reg 8 o r_data_read [7:0] $end
$var reg 1 p r_en $end
$var reg 8 q r_functions [7:0] $end
$var reg 16 r r_period [15:0] $end
$var reg 8 s r_prescale [7:0] $end
$var reg 1 t r_pwm_en $end
$var reg 1 u r_upnotdown $end
$upscope $end
$scope module i_spi_bridge $end
$var wire 1 H byte_sync $end
$var wire 1 2 clk $end
$var wire 1 4 cs_n $end
$var wire 8 v data_in [7:0] $end
$var wire 8 w data_out [7:0] $end
$var wire 1 ! miso $end
$var wire 1 7 mosi $end
$var wire 1 5 rst_n $end
$var wire 1 6 sclk $end
$var reg 3 x bit_cnt [2:0] $end
$var reg 1 y byte_ready $end
$var reg 1 z r_byte_sync $end
$var reg 8 { r_data_in [7:0] $end
$var reg 1 | r_miso $end
$var reg 8 } shift_reg [7:0] $end
$upscope $end
$upscope $end
$scope task apply_reset $end
$upscope $end
$scope task check_pwm_duty $end
$var integer 32 ~ exp [31:0] $end
$var integer 32 !" high_count [31:0] $end
$var integer 32 "" high_per_period [31:0] $end
$var integer 32 #" i [31:0] $end
$var integer 32 $" num_periods [31:0] $end
$var integer 32 %" period_val [31:0] $end
$var integer 32 &" total_ticks [31:0] $end
$upscope $end
$scope task spi_read_reg $end
$var reg 6 '" addr [5:0] $end
$var reg 8 (" cmd [7:0] $end
$var reg 8 )" data [7:0] $end
$var reg 8 *" rx [7:0] $end
$upscope $end
$scope task spi_transfer_byte $end
$var reg 8 +" rx [7:0] $end
$var reg 8 ," tx [7:0] $end
$var integer 32 -" i [31:0] $end
$upscope $end
$scope task spi_write_reg $end
$var reg 6 ." addr [5:0] $end
$var reg 8 /" cmd [7:0] $end
$var reg 8 0" data [7:0] $end
$var reg 8 1" dummy [7:0] $end
$upscope $end
$upscope $end
$enddefinitions $end
$comment Show the parameter values. $end
$dumpall
1U
0T
b110010 1
b1011 0
b1100 /
b1010 .
b0 -
b1101 ,
b1000 +
b111 *
b10 )
b101 (
b11 '
b10 &
b1 %
b0 $
b110010 #
$end
#0
$dumpvars
bx 1"
bx 0"
bx /"
bx ."
bx -"
bx ,"
bx +"
bx *"
bx )"
bx ("
bx '"
bx &"
bx %"
bx $"
bx #"
bx ""
bx !"
bx ~
b0 }
0|
b0 {
0z
0y
b0 x
b0 w
b0 v
0u
0t
b0 s
b0 r
b0 q
0p
b0 o
0n
b0 m
b0 l
b0 k
b0 j
b0 i
b0 h
b0 g
b0 f
b0 e
b0 d
b0 c
0b
b0 a
b0 `
b0 _
b0 ^
b0 ]
0\
0[
0Z
0Y
b0 X
b0 W
b0 V
b0 S
b0 R
b0 Q
b0 P
b0 O
b0 N
b0 M
b0 L
b0 K
b0 J
b0 I
0H
b0 G
b0 F
0E
b0 D
b0 C
b0 B
b0 A
b0 @
0?
b0 >
b0 =
b0 <
0;
0:
09
08
07
06
05
14
bx 3
02
0"
0!
$end
#50
12
#100
02
#150
12
#200
02
#250
12
#300
02
#350
12
#400
02
#450
12
#500
02
15
#550
12
#600
02
#650
12
#700
02
#750
12
b11000000 /"
b111 0"
b0 ."
#800
02
17
b111 -"
b0 +"
b11000000 ,"
04
#850
b1 x
b1 }
12
16
#900
b110 -"
06
02
#950
b10 x
b11 }
16
12
#1000
07
b101 -"
06
02
#1050
b11 x
b110 }
16
12
#1100
b100 -"
06
02
#1150
b100 x
b1100 }
16
12
#1200
b11 -"
06
02
#1250
b101 x
b11000 }
16
12
#1300
b10 -"
06
02
#1350
b110 x
b110000 }
16
12
#1400
b1 -"
06
02
#1450
b111 x
b1100000 }
16
12
#1500
b0 -"
06
02
#1550
1y
b0 x
b11000000 }
16
12
#1600
b111 ,"
b0 1"
b111 -"
06
02
#1650
0y
b1 x
b10000000 }
b11000000 C
b11000000 S
b11000000 v
b11000000 {
1H
1z
16
12
#1700
b110 -"
06
02
#1750
b10 x
b0 }
0H
0z
1[
1Z
16
12
#1800
b101 -"
06
02
#1850
b11 x
16
12
#1900
b100 -"
06
02
#1950
b100 x
16
12
#2000
b11 -"
06
02
#2050
b101 x
16
12
#2100
17
b10 -"
06
02
#2150
b110 x
b1 }
16
12
#2200
b1 -"
06
02
#2250
b111 x
b11 }
16
12
#2300
b0 -"
06
02
#2350
1y
b0 x
b111 }
16
12
#2400
b11111111111111111111111111111111 -"
06
02
#2450
0y
b111 C
b111 S
b111 v
b111 {
1H
1z
14
12
#2500
02
#2550
0H
0z
0[
18
1\
b111 @
b111 Q
b111 h
b111 X
12
#2600
02
#2650
b111 =
b111 L
b111 ^
b111 j
b111 r
08
0\
12
b11001010 /"
b0 0"
b1010 ."
#2700
02
b111 -"
b11001010 ,"
04
#2750
b1 x
b1111 }
12
16
#2800
b110 -"
06
02
#2850
b10 x
b11111 }
16
12
#2900
07
b101 -"
06
02
#2950
b11 x
b111110 }
16
12
#3000
b100 -"
06
02
#3050
b100 x
b1111100 }
16
12
#3100
17
b11 -"
06
02
#3150
b101 x
b11111001 }
16
12
#3200
07
b10 -"
06
02
#3250
b110 x
b11110010 }
16
12
#3300
17
b1 -"
06
02
#3350
b111 x
b11100101 }
16
12
#3400
07
b0 -"
06
02
#3450
1y
b0 x
b11001010 }
16
12
#3500
b0 ,"
b111 -"
06
02
#3550
0y
b1 x
b10010100 }
b11001010 C
b11001010 S
b11001010 v
b11001010 {
1H
1z
16
12
#3600
b110 -"
06
02
#3650
b10 x
b101000 }
1[
b1010 I
b1010 O
b1010 c
b1010 V
0H
0z
16
12
#3700
b101 -"
06
02
#3750
b11 x
b1010000 }
16
12
#3800
b100 -"
06
02
#3850
b100 x
b10100000 }
16
12
#3900
b11 -"
06
02
#3950
b101 x
b1000000 }
16
12
#4000
b10 -"
06
02
#4050
b110 x
b10000000 }
16
12
#4100
b1 -"
06
02
#4150
b111 x
b0 }
16
12
#4200
b0 -"
06
02
#4250
1y
b0 x
16
12
#4300
b11111111111111111111111111111111 -"
06
02
#4350
0y
b0 C
b0 S
b0 v
b0 {
1H
1z
14
12
#4400
02
#4450
0[
18
1\
b0 @
b0 Q
b0 h
b0 X
0H
0z
12
#4500
02
#4550
08
0\
12
b11000011 /"
b11 0"
b11 ."
#4600
02
17
b111 -"
b11000011 ,"
04
#4650
b1 x
b1 }
12
16
#4700
b110 -"
06
02
#4750
b10 x
b11 }
16
12
#4800
07
b101 -"
06
02
#4850
b11 x
b110 }
16
12
#4900
b100 -"
06
02
#4950
b100 x
b1100 }
16
12
#5000
b11 -"
06
02
#5050
b101 x
b11000 }
16
12
#5100
b10 -"
06
02
#5150
b110 x
b110000 }
16
12
#5200
17
b1 -"
06
02
#5250
b111 x
b1100001 }
16
12
#5300
b0 -"
06
02
#5350
1y
b0 x
b11000011 }
16
12
#5400
07
b11 ,"
b111 -"
06
02
#5450
0y
b1 x
b10000110 }
b11000011 C
b11000011 S
b11000011 v
b11000011 {
1H
1z
16
12
#5500
b110 -"
06
02
#5550
b10 x
b1100 }
0H
0z
1[
b11 I
b11 O
b11 c
b11 V
16
12
#5600
b101 -"
06
02
#5650
b11 x
b11000 }
16
12
#5700
b100 -"
06
02
#5750
b100 x
b110000 }
16
12
