pwm_gen.v
module pwm_gen (
    // peripheral clock signals
    input clk,
    input rst_n,
    // PWM signal register configuration
    input pwm_en,
    input[15:0] period,
    input[7:0] functions,
    input[15:0] compare1,
    input[15:0] compare2,
    input[15:0] count_val,
    // top facing signals
    output pwm_out
);
    wire align_mode = functions[1]; // 0 = aliniat, 1 = nealiniat
    wire align_right = functions[0]; // 0 = left, 1 = right

    reg r_pwm;

    always @(*) begin
        if (!pwm_en) begin
            r_pwm = 1'b0;
        end else if (compare1 == compare2) begin
            // Caz special: daca compare1 == compare2, PWM e mereu 0
            // (intervalul de activare are latime 0)
            r_pwm = 1'b0;
        end else begin
            if (!align_mode) begin
                // Mod aliniat
                if (!align_right) begin
                    // Align left: PWM e HIGH cand count_val <= compare1
                    // Caz special: daca compare1 == 0, PWM nu se activeaza niciodata
                    if (compare1 == 16'd0)
                        r_pwm = 1'b0;
                    else if (count_val <= compare1)
                        r_pwm = 1'b1;
                    else
                        r_pwm = 1'b0;
                end else begin
                    // Align right: PWM e HIGH cand count_val >= compare1
                    if (count_val < compare1)
                        r_pwm = 1'b0;
                    else
                        r_pwm = 1'b1;
                end
            end else begin
                // Mod nealiniat: HIGH intre compare1 si compare2
                if (count_val < compare1) begin
                    r_pwm = 1'b0;
                end else if (count_val < compare2) begin
                    r_pwm = 1'b1;
                end else begin
                    r_pwm = 1'b0;
                end
            end
        end
    end

    assign pwm_out = r_pwm;
endmodule

counter.v
module counter (
    // peripheral clock signals
    input clk,
    input rst_n,
    // register facing signals
    output[15:0] count_val,
    input[15:0] period,
    input en,
    input count_reset,
    input upnotdown,
    input[7:0] prescale
);
    // contorul principal
    reg[15:0] r_count;
    assign count_val = r_count;

    // prescalerul intern
    reg[15:0] r_psc;

    // numarul de cicluri necesar pentru incrementare
    wire[15:0] psc_limit = (16'd1 << prescale);

    always @(posedge clk or negedge rst_n) begin
        if(!rst_n) begin
            r_count <= 16'd0;
            r_psc <= 16'd0;
        end else if(count_reset) begin
            r_count <= 16'd0;
            r_psc <= 16'd0;
        end else begin
            if(!en) begin // contor disabled
                r_psc <= 16'd0; // mentinem prescalerul sincron
            end else begin // contor enabled
                r_psc <= r_psc + 16'd1;

                // daca prescalerul a ajuns la limita, actualizam contorul
                if(r_psc == psc_limit - 1) begin
                    r_psc <= 16'd0;

                    if(upnotdown) begin
                        if (r_count == period)
                            r_count <= 16'd0; // overflow, deci reia de la 0
                        else
                            r_count <= r_count + 16'd1;
                    end
                    else begin
                        if (r_count == 0)
                            r_count <= period; // underflow deci, sarim la PERIOD
                        else
                            r_count <= r_count - 16'd1;
                    end
                end
            end
        end
    end

endmodule

regs.v
module regs (
    // peripheral clock signals
    input clk,
    input rst_n,
    // decoder facing signals
    input read,
    input write,
    input [5:0] addr,
    output [7:0] data_read,
    input  [7:0] data_write,
    // counter programming signals
    input  [15:0] counter_val,
    output [15:0] period,
    output en,
    output count_reset,
    output upnotdown,
    output [7:0] prescale,
    // PWM signal programming values
    output pwm_en,
    output [7:0] functions,
    output [15:0] compare1,
    output [15:0] compare2
);

    // -----------------------------
    // Registre interne
    // -----------------------------
    reg [15:0] r_period;
    reg        r_en;
    reg        r_count_reset;
    reg        r_upnotdown;
    reg [7:0]  r_prescale;
    reg        r_pwm_en;
    reg [7:0]  r_functions;
    reg [15:0] r_compare1;
    reg [15:0] r_compare2;
    reg [7:0]  r_data_read;

    // -----------------------------
    // Conectări către ieșiri
    // -----------------------------
    assign period     = r_period;
    assign en         = r_en;
    assign count_reset = r_count_reset;
    assign upnotdown  = r_upnotdown;
    assign prescale   = r_prescale;
    assign pwm_en     = r_pwm_en;
    assign functions  = r_functions;
    assign compare1   = r_compare1;
    assign compare2   = r_compare2;
    assign data_read  = r_data_read;

    // -----------------------------
    // LOGICA DE SCRIERE
    // -----------------------------
    always @(posedge clk or negedge rst_n) begin
        if (!rst_n) begin
            r_period      <= 16'h0000;
            r_en          <= 1'b0;
            r_count_reset <= 1'b0;
            r_upnotdown   <= 1'b0;
            r_prescale    <= 8'h00;
            r_pwm_en      <= 1'b0;
            r_functions   <= 8'h00;
            r_compare1    <= 16'h0000;
            r_compare2    <= 16'h0000;
        end else begin
            r_count_reset <= 1'b0; // puls de un ciclu

            if (write) begin
                case (addr)
                    6'h00: r_period[7:0]   <= data_write;
                    6'h01: r_period[15:8]  <= data_write;
                    6'h02: r_en            <= data_write[0];
                    6'h03: r_compare1[7:0] <= data_write;
                    6'h04: r_compare1[15:8] <= data_write;
                    6'h05: r_compare2[7:0] <= data_write;
                    6'h06: r_compare2[15:8] <= data_write;
                    6'h07: r_count_reset   <= 1'b1; // write-only
                    6'h0A: r_prescale      <= data_write;
                    6'h0B: r_upnotdown     <= data_write[0];
                    6'h0C: r_pwm_en        <= data_write[0];
                    6'h0D: r_functions     <= data_write;
                endcase
            end
        end
    end

    // -----------------------------
    // LOGICA DE CITIRE
    // -----------------------------
    always @(*) begin
        if (!read) begin
            r_data_read = 8'h00;
        end else begin
            case (addr)
                6'h00: r_data_read = r_period[7:0];
                6'h01: r_data_read = r_period[15:8];
                6'h02: r_data_read = {7'd0, r_en};
                6'h03: r_data_read = r_compare1[7:0];
                6'h04: r_data_read = r_compare1[15:8];
                6'h05: r_data_read = r_compare2[7:0];
                6'h06: r_data_read = r_compare2[15:8];
                6'h07: r_data_read = 8'h00; // write-only
                6'h08: r_data_read = counter_val[7:0];
                6'h09: r_data_read = counter_val[15:8];
                6'h0A: r_data_read = r_prescale;
                6'h0B: r_data_read = {7'd0, r_upnotdown};
                6'h0C: r_data_read = {7'd0, r_pwm_en};
                6'h0D: r_data_read = r_functions;
                default: r_data_read = 8'h00;
            endcase
        end
    end

endmodule

instr_dcd.v
module instr_dcd (
    // peripheral clock signals
    input clk,
    input rst_n,
    // towards SPI slave interface signals
    input byte_sync,
    input [7:0] data_in,
    output [7:0] data_out,
    // register access signals
    output read,
    output write,
    output [5:0] addr,
    input [7:0] data_read,
    output [7:0] data_write
);
    // registri pentru outputuri
    reg r_read;
    reg r_write;
    reg [5:0] r_addr;
    reg [7:0] r_data_write;

    // legam iesirile
    assign read = r_read;
    assign write = r_write;
    assign addr = r_addr;
    assign data_write = r_data_write;

    assign data_out = (r_read) ? data_read : 8'h00;

    // logica de FSM
    reg state;
    reg next_state;
    reg is_read_op;

    // selectia pentru MSB/LSB
    reg byte_sel;

    // adresa de baza (fara bitul 6)
    reg [5:0] base_addr;

    localparam ST_SETUP = 0;
    localparam ST_DATA = 1;

    always @(*) begin
        next_state = state;
        case (state)
            ST_SETUP: begin
                if (byte_sync) next_state = ST_DATA;
            end
            ST_DATA: begin
                if (byte_sync) next_state = ST_SETUP;
            end
        endcase
    end

    always @(posedge clk or negedge rst_n) begin
        if(!rst_n) begin
            state <= ST_SETUP;
            r_read <= 0;
            r_write <= 0;
            r_addr <= 0;
            r_data_write <= 0;
            is_read_op <= 0;
            base_addr <= 0;
            byte_sel <= 0;
        end
        else begin
            r_write <= 0; // trebuie resetat la 0 la fiecare ciclu, il setam la 1 doar cand vrem

            if(byte_sync) begin
                case(state)
                    ST_SETUP: begin
                        // bitul 7: 1 = write, 0 = read
                        is_read_op <= (data_in[7] == 0);

                        // bitul 6: MSB/LSB select (informational, nu modifica adresa)
                        byte_sel <= data_in[6];

                        // bits 5:0 = adresa directa
                        base_addr <= data_in[5:0];

                        // adresa e folosita direct, fara offset
                        r_addr <= data_in[5:0];

                        // setam r_read pentru READ operations
                        r_read <= (data_in[7] == 0);

                        state <= ST_DATA;
                    end

                    ST_DATA: begin
                        // Pentru WRITE, folosim adresa direct (byte_sel nu modifica adresa)
                        if(!is_read_op) begin
                            r_addr <= base_addr;
                            // daca e scriere, luam datele primite si le trimitem la registrii
                            r_data_write <= data_in;
                            r_write <= 1; // activam write mode
                        end

                        // dupa faza de date, dezactivam citirea
                        r_read <= 0;

                        state <= ST_SETUP;
                    end
                endcase
            end
        end
    end

endmodule

spi_bridge.v
module spi_bridge (
    // peripheral clock signals
    input clk,
    input rst_n,
    // SPI master facing signals
    input sclk,
    input cs_n,
    input mosi,
    output miso,
    // internal facing
    output byte_sync,
    output[7:0] data_in,
    input[7:0] data_out
);
    // Registri de iesire
    reg r_miso;
    reg r_byte_sync;
    reg [7:0] r_data_in;

    assign miso = r_miso;
    assign byte_sync = r_byte_sync;
    assign data_in = r_data_in;

    // Logica SPI - functioneaza pe sclk
    reg [2:0] bit_cnt;
    reg [7:0] shift_reg;
    
    // Counter pentru byte-uri complete (incrementat pe sclk domain)
    reg [7:0] byte_counter;
    reg [7:0] byte_counter_sync1;
    reg [7:0] byte_counter_sync2;
    reg [7:0] byte_counter_prev;
    
    // Date capturate
    reg [7:0] captured_data;

    // Logica pe rising edge sclk - captura date de pe mosi
    always @(posedge sclk or negedge rst_n) begin
        if (!rst_n) begin
            bit_cnt <= 0;
            shift_reg <= 0;
            byte_counter <= 0;
            captured_data <= 0;
        end else if (cs_n) begin
            bit_cnt <= 0;
        end else begin
            // Shift in MOSI bit
            shift_reg <= {shift_reg[6:0], mosi};
            
            if (bit_cnt == 7) begin
                bit_cnt <= 0;
                captured_data <= {shift_reg[6:0], mosi};
                byte_counter <= byte_counter + 1;
            end else begin
                bit_cnt <= bit_cnt + 1;
            end
        end
    end
    
    // Logica pe falling edge sclk - setare MISO
    always @(negedge sclk or negedge rst_n) begin
        if (!rst_n) begin
            r_miso <= 0;
        end else if (!cs_n) begin
            // Output next bit (MSB first)
            r_miso <= data_out[7 - bit_cnt];
        end
    end
    
    // Prima setare MISO cand CS devine activ
    always @(negedge cs_n or negedge rst_n) begin
        if (!rst_n) begin
            // handled above
        end else begin
            r_miso <= data_out[7];
        end
    end

    // Sincronizare byte_counter catre domeniul clk
    always @(posedge clk or negedge rst_n) begin
        if (!rst_n) begin
            byte_counter_sync1 <= 0;
            byte_counter_sync2 <= 0;
            byte_counter_prev <= 0;
            r_byte_sync <= 0;
            r_data_in <= 0;
        end else begin
            // Double-sync byte_counter
            byte_counter_sync1 <= byte_counter;
            byte_counter_sync2 <= byte_counter_sync1;
            byte_counter_prev <= byte_counter_sync2;
            
            // Detecteaza cand s-a completat un byte nou
            r_byte_sync <= 0;
            if (byte_counter_sync2 != byte_counter_prev) begin
                r_byte_sync <= 1;
                r_data_in <= captured_data;
            end
        end
    end

endmodule

top.v
module top(
    input clk,
    input rst_n,
    input sclk,
    input cs_n,
    input miso,
    output mosi,
    output pwm_out
);

// NU SE REDECLARĂ PORTURILE !!!
// DOAR se declară semnalele interne CE NU SUNT PORTURI.

wire byte_sync;
wire [7:0] data_in;
wire [7:0] data_out;

wire read;
wire write;
wire [5:0] addr;

wire [7:0] data_read;
wire [7:0] data_write;

wire [15:0] counter_val;
wire [15:0] period;

wire en;
wire count_reset;
wire upnotdown;

wire [7:0] prescale;
wire pwm_en;

wire [7:0] functions;
wire [15:0] compare1;
wire [15:0] compare2;

spi_bridge i_spi_bridge (
    .clk(clk),
    .rst_n(rst_n),
    .sclk(sclk),
    .cs_n(cs_n),
    .miso(mosi),  // bridge.miso (OUTPUT) -> top.mosi (output) - compensare pentru conventie inversata
    .mosi(miso),  // bridge.mosi (INPUT) <- top.miso (input) - compensare pentru conventie inversata
    .byte_sync(byte_sync),
    .data_in(data_in),
    .data_out(data_out)
);

instr_dcd i_instr_dcd (
    .clk(clk),
    .rst_n(rst_n),
    .byte_sync(byte_sync),
    .data_in(data_in),
    .data_out(data_out),
    .read(read),
    .write(write),
    .addr(addr),
    .data_read(data_read),
    .data_write(data_write)
);

regs i_regs (
    .clk(clk),
    .rst_n(rst_n),
    .read(read),
    .write(write),
    .addr(addr),
    .data_read(data_read),
    .data_write(data_write),
    .counter_val(counter_val),
    .period(period),
    .en(en),
    .count_reset(count_reset),
    .upnotdown(upnotdown),
    .prescale(prescale),
    .pwm_en(pwm_en),
    .functions(functions),
    .compare1(compare1),
    .compare2(compare2)
);

counter i_counter (
    .clk(clk),
    .rst_n(rst_n),
    .count_val(counter_val),
    .period(period),
    .en(en),
    .count_reset(count_reset),
    .upnotdown(upnotdown),
    .prescale(prescale)
);

pwm_gen i_pwm_gen (
    .clk(clk),
    .rst_n(rst_n),
    .pwm_en(pwm_en),
    .period(period),
    .functions(functions),
    .compare1(compare1),
    .compare2(compare2),
    .count_val(counter_val),
    .pwm_out(pwm_out)
);

endmodule

testbench.v
`default_nettype none
`timescale 1ns/1ns

module tb_top_system;

    reg  clk;        
    reg  rst_n;

    reg  tb_mosi;   
    wire tb_miso;    
    reg  sclk;      
    reg  cs_n;       

    wire pwm_out;

    reg[7:0] counter_lsb;

    top dut (
        .clk    (clk),
        .rst_n  (rst_n),
        .sclk   (sclk),
        .cs_n   (cs_n),
        .miso   (tb_mosi),
        .mosi   (tb_miso),
        .pwm_out(pwm_out)
    );

    localparam CLK_HALF   = 50;  
    localparam SCLK_HALF  = 50;   

    localparam [5:0] REG_PERIOD        = 6'h00;
    localparam [5:0] REG_COUNTER_EN    = 6'h02;
    localparam [5:0] REG_COMPARE1      = 6'h03;
    localparam [5:0] REG_COMPARE2      = 6'h05;
    localparam [5:0] REG_COUNTER_RESET = 6'h07;
    localparam [5:0] REG_COUNTER_VAL   = 6'h08;
    localparam [5:0] REG_PRESCALE      = 6'h0A;
    localparam [5:0] REG_UPNOTDOWN     = 6'h0B;
    localparam [5:0] REG_PWM_EN        = 6'h0C;
    localparam [5:0] REG_FUNCTIONS     = 6'h0D;

    localparam [1:0] FUNCTION_ALIGN_LEFT             = 2'b00;
    localparam [1:0] FUNCTION_ALIGN_RIGHT            = 2'b01;
    localparam [1:0] FUNCTION_RANGE_BETWEEN_COMPARES = 2'b10;

    initial begin
        clk = 1'b0;
        forever #(CLK_HALF) clk = ~clk;
    end

    initial begin
        $dumpfile("waves.vcd");
        $dumpvars(0, tb_top_system);
    end

    task apply_reset;
        begin
            rst_n  = 1'b0;
            cs_n   = 1'b1;
            sclk   = 1'b0;
            tb_mosi = 1'b0;
            #(10*CLK_HALF); 
            rst_n  = 1'b1;
            #(5*CLK_HALF);
            $display("Time %0t: Reset deasserted.", $time);
        end
    endtask

    task spi_transfer_byte;
        input  [7:0] tx;
        output [7:0] rx;
        integer i;
        begin
            rx = 8'h00;
            for (i = 7; i >= 0; i = i - 1) begin
                tb_mosi = tx[i];
                #(SCLK_HALF);
                sclk = 1'b1;           
                #(SCLK_HALF/2);
                rx[i] = tb_miso;      
                #(SCLK_HALF/2);
                sclk = 1'b0;
            end
        end
    endtask

    task spi_write_reg;
        input  [5:0] addr;
        input  [7:0] data;
        reg    [7:0] cmd;
        reg    [7:0] dummy;
        begin
            cmd = {1'b1, 1'b1, addr};   
            #(SCLK_HALF);
            cs_n = 1'b0;

            spi_transfer_byte(cmd, dummy);
            spi_transfer_byte(data, dummy);

            #(SCLK_HALF);
            cs_n = 1'b1;

            $display("Time %0t: SPI WRITE  addr=0x%02h  data=0x%02h", $time, addr, data);
            #(4*CLK_HALF); 
        end
    endtask

    task spi_read_reg;
        input  [5:0] addr;
        output [7:0] data;
        reg    [7:0] cmd;
        reg    [7:0] rx;
        begin
            cmd = {1'b0, 1'b1, addr};   
            #(SCLK_HALF);
            cs_n = 1'b0;

            spi_transfer_byte(cmd, rx);           
            spi_transfer_byte(8'h00, data);     

            #(SCLK_HALF);
            cs_n = 1'b1;

            $display("Time %0t: SPI READ   addr=0x%02h  data=0x%02h", $time, addr, data);
            #(4*CLK_HALF);
        end
    endtask

    task check_pwm_duty;
        input integer period_val;
        input integer high_per_period;
        input integer num_periods;
        integer total_ticks;
        integer high_count;
        integer i;
        integer exp;
        begin
            total_ticks = (period_val + 1) * num_periods;
            exp         = high_per_period * num_periods;
            high_count  = 0;

            #(5*CLK_HALF);

            for (i = 0; i < total_ticks; i = i + 1) begin
                @(posedge clk);
                if (pwm_out)
                    high_count = high_count + 1;
            end

            if ((high_count >= exp-1) && (high_count <= exp+1)) begin
                $display("[PASS] PWM duty aprox. corect: high=%0d, expected ~%0d", 
                         high_count, exp);
            end else begin
                $display("[FAIL] PWM duty incorect: high=%0d, expected %0d", 
                         high_count, exp);
            end
        end
    endtask

    initial begin
        $display("--- Starting Testbench ---");

        rst_n   = 1'b0;
        cs_n    = 1'b1;
        sclk    = 1'b0;
        tb_mosi = 1'b0;

        apply_reset();

        spi_write_reg(REG_PERIOD,       8'd7);
        spi_write_reg(REG_PRESCALE,     8'd0);
        spi_write_reg(REG_COMPARE1,     8'd3);
        spi_write_reg(REG_COUNTER_EN,   8'd1);
        spi_write_reg(REG_PWM_EN,       8'd1);
        spi_write_reg(REG_FUNCTIONS,    {6'b0, FUNCTION_ALIGN_LEFT});

        spi_write_reg(REG_COUNTER_RESET, 8'd1);
        spi_write_reg(REG_COUNTER_RESET, 8'd0);

        $display("\n--- Test 1: PWM ALIGN_LEFT, compare1=3, period=7 ---");
        check_pwm_duty(7, 4, 5); 


        spi_read_reg(REG_COUNTER_VAL, counter_lsb);

        $display("\n--- Test 2: PWM RANGE_BETWEEN_COMPARES, c1=2, c2=6 ---");
        spi_write_reg(REG_COMPARE1, 8'd2);
        spi_write_reg(REG_COMPARE2, 8'd6);
        spi_write_reg(REG_FUNCTIONS, {6'b0, FUNCTION_RANGE_BETWEEN_COMPARES});

        check_pwm_duty(7, 4, 5); 

        $display("\n--- Test 3: PWM ALIGN_RIGHT, compare1=5 ---");
        spi_write_reg(REG_COMPARE1, 8'd5);
        spi_write_reg(REG_FUNCTIONS, {6'b0, FUNCTION_ALIGN_RIGHT});

        check_pwm_duty(7, 3, 5); 

        $display("\n--- Test 4: PWM UNALIGNED EDGE CASE EQUAL COMPARES ---");
        spi_write_reg(REG_COUNTER_EN, 8'h00);
        spi_write_reg(REG_COMPARE1, 8'h05);
        spi_write_reg(REG_COMPARE2, 8'h05);
        spi_write_reg(REG_COUNTER_EN, 8'h01);
        check_pwm_duty(7, 0, 2);
        
        $display("\n--- Test 5: PWM NOT TRIGGER AT START, compare1=0 ---");
        spi_write_reg(REG_COUNTER_EN, 8'h00);
        spi_write_reg(REG_COMPARE1, 8'h00);
        spi_write_reg(REG_FUNCTIONS, 8'h00);
        spi_write_reg(REG_COUNTER_EN, 8'h01);
        check_pwm_duty(7, 0, 3);

        $display("\n--- Finished Testbench ---");
        $finish;
    end

endmodule

`default_nettype wire

waves.vcd
$date
	Sun Dec 14 16:38:40 2025
$end
$version
	Icarus Verilog
$end
$timescale
	1ns
$end
$scope module tb_top_system $end
$var wire 1 ! tb_miso $end
$var wire 1 " pwm_out $end
$var parameter 32 # CLK_HALF $end
$var parameter 2 $ FUNCTION_ALIGN_LEFT $end
$var parameter 2 % FUNCTION_ALIGN_RIGHT $end
$var parameter 2 & FUNCTION_RANGE_BETWEEN_COMPARES $end
$var parameter 6 ' REG_COMPARE1 $end
$var parameter 6 ( REG_COMPARE2 $end
$var parameter 6 ) REG_COUNTER_EN $end
$var parameter 6 * REG_COUNTER_RESET $end
$var parameter 6 + REG_COUNTER_VAL $end
$var parameter 6 , REG_FUNCTIONS $end
$var parameter 6 - REG_PERIOD $end
$var parameter 6 . REG_PRESCALE $end
$var parameter 6 / REG_PWM_EN $end
$var parameter 6 0 REG_UPNOTDOWN $end
$var parameter 32 1 SCLK_HALF $end
$var reg 1 2 clk $end
$var reg 8 3 counter_lsb [7:0] $end
$var reg 1 4 cs_n $end
$var reg 1 5 rst_n $end
$var reg 1 6 sclk $end
$var reg 1 7 tb_mosi $end
$scope module dut $end
$var wire 1 2 clk $end
$var wire 1 4 cs_n $end
$var wire 1 7 miso $end
$var wire 1 5 rst_n $end
$var wire 1 6 sclk $end
$var wire 1 8 write $end
$var wire 1 9 upnotdown $end
$var wire 1 : read $end
$var wire 1 " pwm_out $end
$var wire 1 ; pwm_en $end
$var wire 8 < prescale [7:0] $end
$var wire 16 = period [15:0] $end
$var wire 1 ! mosi $end
$var wire 8 > functions [7:0] $end
$var wire 1 ? en $end
$var wire 8 @ data_write [7:0] $end
$var wire 8 A data_read [7:0] $end
$var wire 8 B data_out [7:0] $end
$var wire 8 C data_in [7:0] $end
$var wire 16 D counter_val [15:0] $end
$var wire 1 E count_reset $end
$var wire 16 F compare2 [15:0] $end
$var wire 16 G compare1 [15:0] $end
$var wire 1 H byte_sync $end
$var wire 6 I addr [5:0] $end
$scope module i_counter $end
$var wire 1 2 clk $end
$var wire 16 J count_val [15:0] $end
$var wire 1 5 rst_n $end
$var wire 1 9 upnotdown $end
$var wire 16 K psc_limit [15:0] $end
$var wire 8 L prescale [7:0] $end
$var wire 16 M period [15:0] $end
$var wire 1 ? en $end
$var wire 1 E count_reset $end
$var reg 16 N r_count [15:0] $end
$var reg 16 O r_psc [15:0] $end
$upscope $end
$scope module i_instr_dcd $end
$var wire 6 P addr [5:0] $end
$var wire 1 2 clk $end
$var wire 8 Q data_write [7:0] $end
$var wire 1 : read $end
$var wire 1 5 rst_n $end
$var wire 1 8 write $end
$var wire 8 R data_read [7:0] $end
$var wire 8 S data_out [7:0] $end
$var wire 8 T data_in [7:0] $end
$var wire 1 H byte_sync $end
$var parameter 32 U ST_DATA $end
$var parameter 32 V ST_SETUP $end
$var reg 6 W base_addr [5:0] $end
$var reg 1 X byte_sel $end
$var reg 1 Y is_read_op $end
$var reg 1 Z next_state $end
$var reg 6 [ r_addr [5:0] $end
$var reg 8 \ r_data_write [7:0] $end
$var reg 1 ] r_read $end
$var reg 1 ^ r_write $end
$var reg 1 _ state $end
$upscope $end
$scope module i_pwm_gen $end
$var wire 1 2 clk $end
$var wire 16 ` count_val [15:0] $end
$var wire 1 " pwm_out $end
$var wire 1 5 rst_n $end
$var wire 1 ; pwm_en $end
$var wire 16 a period [15:0] $end
$var wire 8 b functions [7:0] $end
$var wire 16 c compare2 [15:0] $end
$var wire 16 d compare1 [15:0] $end
$var wire 1 e align_right $end
$var wire 1 f align_mode $end
$var reg 1 g r_pwm $end
$upscope $end
$scope module i_regs $end
$var wire 6 h addr [5:0] $end
$var wire 1 2 clk $end
$var wire 16 i compare1 [15:0] $end
$var wire 16 j compare2 [15:0] $end
$var wire 1 E count_reset $end
$var wire 16 k counter_val [15:0] $end
$var wire 8 l data_write [7:0] $end
$var wire 1 ? en $end
$var wire 16 m period [15:0] $end
$var wire 1 ; pwm_en $end
$var wire 1 : read $end
$var wire 1 5 rst_n $end
$var wire 1 9 upnotdown $end
$var wire 1 8 write $end
$var wire 8 n prescale [7:0] $end
$var wire 8 o functions [7:0] $end
$var wire 8 p data_read [7:0] $end
$var reg 16 q r_compare1 [15:0] $end
$var reg 16 r r_compare2 [15:0] $end
$var reg 1 s r_count_reset $end
$var reg 8 t r_data_read [7:0] $end
$var reg 1 u r_en $end
$var reg 8 v r_functions [7:0] $end
$var reg 16 w r_period [15:0] $end
$var reg 8 x r_prescale [7:0] $end
$var reg 1 y r_pwm_en $end
$var reg 1 z r_upnotdown $end
$upscope $end
$scope module i_spi_bridge $end
$var wire 1 H byte_sync $end
$var wire 1 2 clk $end
$var wire 1 4 cs_n $end
$var wire 8 { data_in [7:0] $end
$var wire 8 | data_out [7:0] $end
$var wire 1 ! miso $end
$var wire 1 7 mosi $end
$var wire 1 5 rst_n $end
$var wire 1 6 sclk $end
$var reg 3 } bit_cnt [2:0] $end
$var reg 8 ~ byte_counter [7:0] $end
$var reg 8 !" byte_counter_prev [7:0] $end
$var reg 8 "" byte_counter_sync1 [7:0] $end
$var reg 8 #" byte_counter_sync2 [7:0] $end
$var reg 8 $" captured_data [7:0] $end
$var reg 1 %" r_byte_sync $end
$var reg 8 &" r_data_in [7:0] $end
$var reg 1 '" r_miso $end
$var reg 8 (" shift_reg [7:0] $end
$upscope $end
$upscope $end
$scope task apply_reset $end
$upscope $end
$scope task check_pwm_duty $end
$var integer 32 )" exp [31:0] $end
$var integer 32 *" high_count [31:0] $end
$var integer 32 +" high_per_period [31:0] $end
$var integer 32 ," i [31:0] $end
$var integer 32 -" num_periods [31:0] $end
$var integer 32 ." period_val [31:0] $end
$var integer 32 /" total_ticks [31:0] $end
$upscope $end
$scope task spi_read_reg $end
$var reg 6 0" addr [5:0] $end
$var reg 8 1" cmd [7:0] $end
$var reg 8 2" data [7:0] $end
$var reg 8 3" rx [7:0] $end
$upscope $end
$scope task spi_transfer_byte $end
$var reg 8 4" rx [7:0] $end
$var reg 8 5" tx [7:0] $end
$var integer 32 6" i [31:0] $end
$upscope $end
$scope task spi_write_reg $end
$var reg 6 7" addr [5:0] $end
$var reg 8 8" cmd [7:0] $end
$var reg 8 9" data [7:0] $end
$var reg 8 :" dummy [7:0] $end
$upscope $end
$upscope $end
$enddefinitions $end
$comment Show the parameter values. $end
$dumpall
b0 V
b1 U
b110010 1
b1011 0
b1100 /
b1010 .
b0 -
b1101 ,
b1000 +
b111 *
b10 )
b101 (
b11 '
b10 &
b1 %
b0 $
b110010 #
$end
#0
$dumpvars
bx :"
bx 9"
bx 8"
bx 7"
bx 6"
bx 5"
bx 4"
bx 3"
bx 2"
bx 1"
bx 0"
bx /"
bx ."
bx -"
bx ,"
bx +"
bx *"
bx )"
b0 ("
0'"
b0 &"
0%"
b0 $"
b0 #"
b0 ""
b0 !"
b0 ~
b0 }
b0 |
b0 {
0z
0y
b0 x
b0 w
b0 v
0u
b0 t
0s
b0 r
b0 q
b0 p
b0 o
b0 n
b0 m
b0 l
b0 k
b0 j
b0 i
b0 h
0g
0f
0e
b0 d
b0 c
b0 b
b0 a
b0 `
0_
0^
0]
b0 \
b0 [
0Z
0Y
0X
b0 W
b0 T
b0 S
b0 R
b0 Q
b0 P
b0 O
b0 N
b0 M
b0 L
b1 K
b0 J
b0 I
0H
b0 G
b0 F
0E
b0 D
b0 C
b0 B
b0 A
b0 @
0?
b0 >
b0 =
b0 <
0;
0:
09
08
07
06
05
14
bx 3
02
0"
0!
$end
#50
12
#100
02
#150
12
#200
02
#250
12
#300
02
#350
12
#400
02
#450
12
#500
02
15
#550
12
#600
02
#650
12
#700
02
#750
12
b11000000 8"
b111 9"
b0 7"
#800
02
17
b111 6"
b0 4"
b11000000 5"
04
#850
b1 }
b1 ("
12
16
#900
b110 6"
06
02
#950
b10 }
b11 ("
16
12
#1000
07
b101 6"
06
02
#1050
b11 }
b110 ("
16
12
#1100
b100 6"
06
02
#1150
b100 }
b1100 ("
16
12
#1200
b11 6"
06
02
#1250
b101 }
b11000 ("
16
12
#1300
b10 6"
06
02
#1350
b110 }
b110000 ("
16
12
#1400
b1 6"
06
02
#1450
b111 }
b1100000 ("
16
12
#1500
b0 6"
06
02
#1550
b1 ~
b11000000 $"
b0 }
b11000000 ("
16
12
#1600
b111 5"
b0 :"
b111 6"
06
02
#1650
b1 }
b10000000 ("
b1 ""
16
12
#1700
b110 6"
06
02
#1750
b10 }
b0 ("
b1 #"
16
12
#1800
b101 6"
06
02
#1850
1Z
b11 }
b11000000 C
b11000000 T
b11000000 {
b11000000 &"
1H
1%"
b1 !"
16
12
#1900
b100 6"
06
02
#1950
b100 }
0H
0%"
1_
1X
16
12
#2000
b11 6"
06
02
#2050
b101 }
16
12
#2100
17
b10 6"
06
02
#2150
b110 }
b1 ("
16
12
#2200
b1 6"
06
02
#2250
b111 }
b11 ("
16
12
#2300
b0 6"
06
02
#2350
b10 ~
b111 $"
b0 }
b111 ("
16
12
#2400
b11111111111111111111111111111111 6"
06
02
#2450
b10 ""
14
12
#2500
02
#2550
b10 #"
12
#2600
02
#2650
0Z
b111 C
b111 T
b111 {
b111 &"
1H
1%"
b10 !"
12
b11001010 8"
b0 9"
b1010 7"
#2700
02
b111 6"
b11001010 5"
04
#2750
0H
0%"
0_
18
1^
b111 @
b111 Q
b111 l
b111 \
b1 }
b1111 ("
12
16
#2800
b110 6"
06
02
#2850
b10 }
b11111 ("
b111 =
b111 M
b111 a
b111 m
b111 w
08
0^
16
12
#2900
07
b101 6"
06
02
#2950
b11 }
b111110 ("
16
12
#3000
b100 6"
06
02
#3050
b100 }
b1111100 ("
16
12
#3100
17
b11 6"
06
02
#3150
b101 }
b11111001 ("
16
12
#3200
07
b10 6"
06
02
#3250
b110 }
b11110010 ("
16
12
#3300
17
b1 6"
06
02
#3350
b111 }
b11100101 ("
16
12
#3400
07
b0 6"
06
02
#3450
b11 ~
b11001010 $"
b0 }
b11001010 ("
16
12
#3500
b0 5"
b111 6"
06
02
#3550
b1 }
b10010100 ("
b11 ""
16
12
#3600
b110 6"
06
02
#3650
b10 }
b101000 ("
b11 #"
16
12
#3700
b101 6"
06
02
#3750
1Z
b11 }
b1010000 ("
b11001010 C
b11001010 T
b11001010 {
b11001010 &"
1H
1%"
b11 !"
16
12
#3800
b100 6"
06
02
#3850
b100 }
b10100000 ("
1_
b1010 I
b1010 P
b1010 h
b1010 [
b1010 W
0H
0%"
16
12
#3900
b11 6"
06
02
#3950
b101 }
b1000000 ("
16
12
#4000
b10 6"
06
02
#4050
b110 }
b10000000 ("
16
12
#4100
b1 6"
06
02
#4150
b111 }
b0 ("
16
12
#4200
b0 6"
06
02
#4250
b100 ~
b0 $"
b0 }
16
12
#4300
b11111111111111111111111111111111 6"
06
02
#4350
b100 ""
14
12
#4400
02
#4450
b100 #"
12
#4500
02
#4550
0Z
b0 C
b0 T
b0 {
b0 &"
1H
1%"
b100 !"
12
b11000011 8"
b11 9"
b11 7"
#4600
02
17
b111 6"
b11000011 5"
04
#4650
0_
18
1^
b0 @
b0 Q
b0 l
b0 \
0H
0%"
b1 }
b1 ("
12
16
#4700
b110 6"
06
02
#4750
b10 }
b11 ("
08
0^
16
12
#4800
07
b101 6"
06
02
#4850
b11 }
b110 ("
16
12
#4900
b100 6"
06
02
#4950
b100 }
b1100 ("
16
12
#5000
b11 6"
06
02
#5050
b101 }
b11000 ("
16
12
