PWM_GEN/pwm_gen.v
module pwm_gen (
    // Semnale ceas periferic
    input clk,
    input rst_n,

    // Configurare din registri
    input pwm_en,
    input [15:0] period,
    input [7:0]  functions,      // bit1 = unaligned, bit0 = align L/R
    input [15:0] compare1,
    input [15:0] compare2,

    // Valoarea curentă a numărătorului
    input [15:0] count_val,

    // Ieșirea către exterior
    output reg pwm_out
);

    wire unaligned = functions[1];
    wire align_lr  = functions[0]; // 0 = stânga, 1 = dreapta

    // Logica PWM
    always @(posedge clk or negedge rst_n) begin
        if (!rst_n) begin
            pwm_out <= 0;
        end else begin

            if (!pwm_en) begin
                // PWM dezactivat → linia rămâne blocată
                pwm_out <= pwm_out;
            end else begin

                // -------------------------
                // RESTART LA OVERFLOW (count_val == period)
                // -------------------------
                if (count_val == period) begin
                    if (!unaligned) begin
                        // PWM ALINIAT
                        pwm_out <= (align_lr == 1'b0) ? 1'b1 : 1'b0;
                    end else begin
                        // PWM NEALINIAT
                        pwm_out <= 1'b0;
                    end
                end

                // -------------------------
                // PWM ALINIAT
                // -------------------------
                if (!unaligned) begin
                    if (count_val == compare1)
                        pwm_out <= ~pwm_out;   // toggle
                end

                // -------------------------
                // PWM NEALINIAT
                // -------------------------
                else begin
                    if (count_val == compare1)
                        pwm_out <= 1'b1;

                    if (count_val == compare2)
                        pwm_out <= 1'b0;
                end

            end
        end
    end

endmodule

PWM_GEN/tb_pwm_gen.v
`timescale 1ns/1ps

module tb_pwm_gen;

    reg clk;
    reg rst_n;

    reg pwm_en;
    reg [15:0] period;
    reg [7:0]  functions;
    reg [15:0] compare1;
    reg [15:0] compare2;
    reg [15:0] count_val;

    wire pwm_out;

    // Instantiere DUT
    pwm_gen dut (
        .clk(clk),
        .rst_n(rst_n),
        .pwm_en(pwm_en),
        .period(period),
        .functions(functions),
        .compare1(compare1),
        .compare2(compare2),
        .count_val(count_val),
        .pwm_out(pwm_out)
    );

    // Clock 10ns
    always #5 clk = ~clk;

    // Simulare counter simplificat pentru test
    task run_counter(input integer cycles);
        integer i;
        begin
            for (i=0; i<cycles; i=i+1) begin
                @(posedge clk);
                count_val <= (count_val == period) ? 0 : count_val + 1;
            end
        end
    endtask

    initial begin
        $dumpfile("pwm_gen.vcd");
        $dumpvars(0, tb_pwm_gen);

        clk = 0;
        rst_n = 0;
        pwm_en = 0;
        period = 10;
        functions = 0;
        compare1 = 3;
        compare2 = 7;
        count_val = 0;

        repeat(3) @(posedge clk);
        rst_n = 1;

        // ================================================================
        // TEST 1 — PWM ALINIAT STÂNGA
        // ================================================================
        $display("\n[TEST 1] PWM Aliniat Stanga");

        functions = 8'b0000_0000; // unaligned=0, align_lr=0 (stânga)
        pwm_en = 1;

        run_counter(40);

        // ================================================================
        // TEST 2 — PWM ALINIAT DREAPTA
        // ================================================================
        $display("\n[TEST 2] PWM Aliniat Dreapta");

        functions = 8'b0000_0001; // unaligned=0, align_lr=1 (dreapta)
        count_val = 0;

        run_counter(40);

        // ================================================================
        // TEST 3 — PWM NEALINIAT
        // ================================================================
        $display("\n[TEST 3] PWM Nealiniat");

        functions = 8'b0000_0010; // unaligned=1
        count_val = 0;

        run_counter(40);

        $display("\n=== SIMULARE TERMINATĂ ===\n");
        $finish;
    end

endmodule

PWM_GEN/pwm_gen.vcd
$date
	Sun Nov 23 21:44:45 2025
$end
$version
	Icarus Verilog
$end
$timescale
	1ps
$end
$scope module tb_pwm_gen $end
$var wire 1 ! pwm_out $end
$var reg 1 " clk $end
$var reg 16 # compare1 [15:0] $end
$var reg 16 $ compare2 [15:0] $end
$var reg 16 % count_val [15:0] $end
$var reg 8 & functions [7:0] $end
$var reg 16 ' period [15:0] $end
$var reg 1 ( pwm_en $end
$var reg 1 ) rst_n $end
$scope module dut $end
$var wire 1 " clk $end
$var wire 16 * compare1 [15:0] $end
$var wire 16 + compare2 [15:0] $end
$var wire 16 , count_val [15:0] $end
$var wire 8 - functions [7:0] $end
$var wire 16 . period [15:0] $end
$var wire 1 ( pwm_en $end
$var wire 1 ) rst_n $end
$var wire 1 / unaligned $end
$var wire 1 0 align_lr $end
$var reg 1 ! pwm_out $end
$upscope $end
$scope task run_counter $end
$var integer 32 1 cycles [31:0] $end
$var integer 32 2 i [31:0] $end
$upscope $end
$upscope $end
$enddefinitions $end
$comment Show the parameter values. $end
$dumpall
$end
#0
$dumpvars
bx 2
bx 1
00
0/
b1010 .
b0 -
b0 ,
b111 +
b11 *
0)
0(
b1010 '
b0 &
b0 %
b111 $
b11 #
0"
0!
$end
#5000
1"
#10000
0"
#15000
1"
#20000
0"
#25000
b0 2
b101000 1
1(
1)
1"
#30000
0"
#35000
b1 %
b1 ,
b1 2
1"
#40000
0"
#45000
b10 %
b10 ,
b10 2
1"
#50000
0"
#55000
b11 %
b11 ,
b11 2
1"
#60000
0"
#65000
1!
b100 %
b100 ,
b100 2
1"
#70000
0"
#75000
b101 %
b101 ,
b101 2
1"
#80000
0"
#85000
b110 %
b110 ,
b110 2
1"
#90000
0"
#95000
b111 %
b111 ,
b111 2
1"
#100000
0"
#105000
b1000 %
b1000 ,
b1000 2
1"
#110000
0"
#115000
b1001 %
b1001 ,
b1001 2
1"
#120000
0"
#125000
b1010 %
b1010 ,
b1010 2
1"
#130000
0"
#135000
b0 %
b0 ,
b1011 2
1"
#140000
0"
#145000
b1 %
b1 ,
b1100 2
1"
#150000
0"
#155000
b10 %
b10 ,
b1101 2
1"
#160000
0"
#165000
b11 %
b11 ,
b1110 2
1"
#170000
0"
#175000
0!
b100 %
b100 ,
b1111 2
1"
#180000
0"
#185000
b101 %
b101 ,
b10000 2
1"
#190000
0"
#195000
b110 %
b110 ,
b10001 2
1"
#200000
0"
#205000
b111 %
b111 ,
b10010 2
1"
#210000
0"
#215000
b1000 %
b1000 ,
b10011 2
1"
#220000
0"
#225000
b1001 %
b1001 ,
b10100 2
1"
#230000
0"
#235000
b1010 %
b1010 ,
b10101 2
1"
#240000
0"
#245000
1!
b0 %
b0 ,
b10110 2
1"
#250000
0"
#255000
b1 %
b1 ,
b10111 2
1"
#260000
0"
#265000
b10 %
b10 ,
b11000 2
1"
#270000
0"
#275000
b11 %
b11 ,
b11001 2
1"
#280000
0"
#285000
0!
b100 %
b100 ,
b11010 2
1"
#290000
0"
#295000
b101 %
b101 ,
b11011 2
1"
#300000
0"
#305000
b110 %
b110 ,
b11100 2
1"
#310000
0"
#315000
b111 %
b111 ,
b11101 2
1"
#320000
0"
#325000
b1000 %
b1000 ,
b11110 2
1"
#330000
0"
#335000
b1001 %
b1001 ,
b11111 2
1"
#340000
0"
#345000
b1010 %
b1010 ,
b100000 2
1"
#350000
0"
#355000
1!
b0 %
b0 ,
b100001 2
1"
#360000
0"
#365000
b1 %
b1 ,
b100010 2
1"
#370000
0"
#375000
b10 %
b10 ,
b100011 2
1"
#380000
0"
#385000
b11 %
b11 ,
b100100 2
1"
#390000
0"
#395000
0!
b100 %
b100 ,
b100101 2
1"
#400000
0"
#405000
b101 %
b101 ,
b100110 2
1"
#410000
0"
#415000
b110 %
b110 ,
b100111 2
1"
#420000
0"
#425000
10
b111 %
b111 ,
b1 &
b1 -
b0 2
1"
#430000
0"
#435000
b1000 %
b1000 ,
b1 2
1"
#440000
0"
#445000
b1001 %
b1001 ,
b10 2
1"
#450000
0"
#455000
b1010 %
b1010 ,
b11 2
1"
#460000
0"
#465000
b0 %
b0 ,
b100 2
1"
#470000
0"
#475000
b1 %
b1 ,
b101 2
1"
#480000
0"
#485000
b10 %
b10 ,
b110 2
1"
#490000
0"
#495000
b11 %
b11 ,
b111 2
1"
#500000
0"
#505000
1!
b100 %
b100 ,
b1000 2
1"
#510000
0"
#515000
b101 %
b101 ,
b1001 2
1"
#520000
0"
#525000
b110 %
b110 ,
b1010 2
1"
#530000
0"
#535000
b111 %
b111 ,
b1011 2
1"
#540000
0"
#545000
b1000 %
b1000 ,
b1100 2
1"
#550000
0"
#555000
b1001 %
b1001 ,
b1101 2
1"
#560000
0"
#565000
b1010 %
b1010 ,
b1110 2
1"
#570000
0"
#575000
0!
b0 %
b0 ,
b1111 2
1"
#580000
0"
#585000
b1 %
b1 ,
b10000 2
1"
#590000
0"
#595000
b10 %
b10 ,
b10001 2
1"
#600000
0"
#605000
b11 %
b11 ,
b10010 2
1"
#610000
0"
#615000
1!
b100 %
b100 ,
b10011 2
1"
#620000
0"
#625000
b101 %
b101 ,
b10100 2
1"
#630000
0"
#635000
b110 %
b110 ,
b10101 2
1"
#640000
0"
#645000
b111 %
b111 ,
b10110 2
1"
#650000
0"
#655000
b1000 %
b1000 ,
b10111 2
1"
#660000
0"
#665000
b1001 %
b1001 ,
b11000 2
1"
#670000
0"
#675000
b1010 %
b1010 ,
b11001 2
1"
#680000
0"
#685000
0!
b0 %
b0 ,
b11010 2
1"
#690000
0"
#695000
b1 %
b1 ,
b11011 2
1"
#700000
0"
#705000
b10 %
b10 ,
b11100 2
1"
#710000
0"
#715000
b11 %
b11 ,
b11101 2
1"
#720000
0"
#725000
1!
b100 %
b100 ,
b11110 2
1"
#730000
0"
#735000
b101 %
b101 ,
b11111 2
1"
#740000
0"
#745000
b110 %
b110 ,
b100000 2
1"
#750000
0"
#755000
b111 %
b111 ,
b100001 2
1"
#760000
0"
#765000
b1000 %
b1000 ,
b100010 2
1"
#770000
0"
#775000
b1001 %
b1001 ,
b100011 2
1"
#780000
0"
#785000
b1010 %
b1010 ,
b100100 2
1"
#790000
0"
#795000
0!
b0 %
b0 ,
b100101 2
1"
#800000
0"
#805000
b1 %
b1 ,
b100110 2
1"
#810000
0"
#815000
b10 %
b10 ,
b100111 2
1"
#820000
0"
#825000
1/
00
b11 %
b11 ,
b10 &
b10 -
b0 2
1"
#830000
0"
#835000
1!
b100 %
b100 ,
b1 2
1"
#840000
0"
#845000
b101 %
b101 ,
b10 2
1"
#850000
0"
#855000
b110 %
b110 ,
b11 2
1"
#860000
0"
#865000
b111 %
b111 ,
b100 2
1"
#870000
0"
#875000
0!
b1000 %
b1000 ,
b101 2
1"
#880000
0"
#885000
b1001 %
b1001 ,
b110 2
1"
#890000
0"
#895000
b1010 %
b1010 ,
b111 2
1"
#900000
0"
#905000
b0 %
b0 ,
b1000 2
1"
#910000
0"
#915000
b1 %
b1 ,
b1001 2
1"
#920000
0"
#925000
b10 %
b10 ,
b1010 2
1"
#930000
0"
#935000
b11 %
b11 ,
b1011 2
1"
#940000
0"
#945000
1!
b100 %
b100 ,
b1100 2
1"
#950000
0"
#955000
b101 %
b101 ,
b1101 2
1"
#960000
0"
#965000
b110 %
b110 ,
b1110 2
1"
#970000
0"
#975000
b111 %
b111 ,
b1111 2
1"
#980000
0"
#985000
0!
b1000 %
b1000 ,
b10000 2
1"
#990000
0"
#995000
b1001 %
b1001 ,
b10001 2
1"
#1000000
0"
#1005000
b1010 %
b1010 ,
b10010 2
1"
#1010000
0"
#1015000
b0 %
b0 ,
b10011 2
1"
#1020000
0"
#1025000
b1 %
b1 ,
b10100 2
1"
#1030000
0"
#1035000
b10 %
b10 ,
b10101 2
1"
#1040000
0"
#1045000
b11 %
b11 ,
b10110 2
1"
#1050000
0"
#1055000
1!
b100 %
b100 ,
b10111 2
1"
#1060000
0"
#1065000
b101 %
b101 ,
b11000 2
1"
#1070000
0"
#1075000
b110 %
b110 ,
b11001 2
1"
#1080000
0"
#1085000
b111 %
b111 ,
b11010 2
1"
#1090000
0"
#1095000
0!
b1000 %
b1000 ,
b11011 2
1"
#1100000
0"
#1105000
b1001 %
b1001 ,
b11100 2
1"
#1110000
0"
#1115000
b1010 %
b1010 ,
b11101 2
1"
#1120000
0"
#1125000
b0 %
b0 ,
b11110 2
1"
#1130000
0"
#1135000
b1 %
b1 ,
b11111 2
1"
#1140000
0"
#1145000
b10 %
b10 ,
b100000 2
1"
#1150000
0"
#1155000
b11 %
b11 ,
b100001 2
1"
#1160000
0"
#1165000
1!
b100 %
b100 ,
b100010 2
1"
#1170000
0"
#1175000
b101 %
b101 ,
b100011 2
1"
#1180000
0"
#1185000
b110 %
b110 ,
b100100 2
1"
#1190000
0"
#1195000
b111 %
b111 ,
b100101 2
1"
#1200000
0"
#1205000
0!
b1000 %
b1000 ,
b100110 2
1"
#1210000
0"
#1215000
b1001 %
b1001 ,
b100111 2
1"
#1220000
0"
#1225000
b1010 %
b1010 ,
b101000 2
1"
