Spi_Bridge/spi_bridge.v
module spi_bridge (
    // peripheral clock signals
    input clk,
    input rst_n,
    // SPI master facing signals
    input sclk,
    input cs_n,
    input mosi,
    output miso,
    // internal facing
    output byte_sync,
    output[7:0] data_in,
    input[7:0] data_out
);
    // declar registrii pentru a folosi in blocurile always
    reg r_miso;
    reg r_byte_sync;
    reg [7:0] r_data_in;

    // legan registrele interne la iesirile modulului
    assign miso = r_miso;
    assign byte_sync = r_byte_sync;
    assign data_in = r_data_in;

    // variabile interne folosite pentru logica
    reg [2:0] bit_cnt; // numara de la 0 la 7 (counter)
    reg [7:0] shift_reg; // retine datele de la MOSI
    reg sclk_prev; // retine starea anterioara a sclk

    wire sclk_rise = (sclk == 1) && (sclk_prev == 0);
    wire sclk_fall = (sclk == 0) && (sclk_prev == 1);

    always @(posedge clk or negedge rst_n) begin
        if(!rst_n) begin
            // reset
            sclk_prev <= 0;
            r_miso <= 0;
            r_byte_sync <= 0;
            r_data_in <= 0;
            bit_cnt <= 0;
            shift_reg <= 0;
        end
        else begin
            sclk_prev <= sclk;
            // pulsul de sync trebuie sa fie 0, il facem 1 doar cand terminam un byte
            r_byte_sync <= 0;

            // SPI functioneaza doar cand Chip Select (CS) este activ (pe Low, adica 0)
            // daca CS e inactiv (High), resetam contorul de biti
            if (cs_n) begin
                bit_cnt <= 0;
            end
            else begin
                // stan MISO pentru primul bit cand CS este activ si bit_cnt = 0
                if (bit_cnt == 0 && !sclk) begin
                    r_miso <= data_out[7];
                end

                if(sclk_rise) begin
                    // pastram ultimii 7 biti si adaugam ultimul bit la sfarsit
                    shift_reg <= {shift_reg[6:0], mosi};

                    // daca am primit 8 biti
                    if(bit_cnt == 7) begin
                        bit_cnt <= 0;
                        r_data_in <= {shift_reg[6:0], mosi};
                        r_byte_sync <= 1;
                    end
                    else begin
                        // incrementam contorul
                        bit_cnt <= bit_cnt + 1;
                    end
                end

                if(sclk_fall) begin
                    // trimitem bit-ul corect din data_out MSB first
                    // cand bit_cnt este 0, trimitem bitul 7. cand e 1, trimitem 6.
                    // (formula este deci: 7 - bit_cnt)
                    r_miso <= data_out[7 - bit_cnt];
                end
            end
        end
    end

endmodule

Spi_Bridge/tb_spi_bridge.v
`timescale 1ns/1ps

module tb_spi_bridge_comprehensive;

    reg clk;
    reg rst_n;
    reg sclk;
    reg cs_n;
    reg mosi;
    wire miso;
    wire byte_sync;
    wire [7:0] data_in;
    reg  [7:0] data_out;
    reg [7:0] miso_captured_byte;

    // Test statistics
    integer test_count;
    integer pass_count;
    integer fail_count;

    // Capture byte_sync pulse
    reg byte_sync_detected;
    reg [7:0] data_in_captured;

    spi_bridge dut (
        .clk(clk),
        .rst_n(rst_n),
        .sclk(sclk),
        .cs_n(cs_n),
        .mosi(mosi),
        .miso(miso),
        .byte_sync(byte_sync),
        .data_in(data_in),
        .data_out(data_out)
    );

    initial clk = 0;
    always #50 clk = ~clk;

    always @(posedge clk) begin
        if (byte_sync) begin
            byte_sync_detected <= 1;
            data_in_captured <= data_in;
        end
    end

    task send_spi_byte;
        input [7:0] byte_to_send;
        input start_cs;
        input end_cs;
        integer i;
        begin
            if (start_cs) begin
                cs_n = 0;
                #1000;
            end

            miso_captured_byte = 0;

            for (i = 7; i >= 0; i = i - 1) begin
                mosi = byte_to_send[i];
                #1000;

                sclk = 1;
                #500;
                miso_captured_byte[i] = miso;
                #500;

                sclk = 0;
                #1000;
            end

            if (end_cs) begin
                #1000;
                cs_n = 1;
                mosi = 0;
                #1000;
            end
        end
    endtask

    task abort_transfer;
        input [7:0] byte_to_send;
        input integer abort_at_bit;
        integer i;
        begin
            cs_n = 0;
            #1000;

            for (i = 7; i >= 0; i = i - 1) begin
                mosi = byte_to_send[i];
                #1000;
                sclk = 1;
                #1000;
                sclk = 0;
                #1000;

                if (i == abort_at_bit) begin
                    cs_n = 1;
                    mosi = 0;
                    #2000;
                    i = -1;
                end
            end
        end
    endtask

    task wait_for_byte_sync;
        integer timeout;
        begin
            timeout = 0;
            while (!byte_sync_detected && timeout < 1000) begin
                @(posedge clk);
                timeout = timeout + 1;
            end
            if (timeout >= 1000)
                $display(" [FAIL] Timeout waiting for byte_sync");
        end
    endtask

    task check_result;
        input [7:0] expected_mosi;
        input [7:0] expected_miso;
        input check_mosi;
        input check_miso;
        input [255:0] test_name;
        begin
            test_count = test_count + 1;

            if (check_mosi) begin
                if (data_in_captured == expected_mosi && byte_sync_detected) begin
                    $display(" [PASS] %0s: MOSI 0x%h", test_name, expected_mosi);
                    pass_count = pass_count + 1;
                end else begin
                    $display(
                      " [FAIL] %0s: MOSI expected 0x%h, got 0x%h (sync=%0d)",
                      test_name,
                      expected_mosi,
                      data_in_captured,
                      byte_sync_detected
                    );
                    fail_count = fail_count + 1;
                end
            end

            if (check_miso) begin
                if (miso_captured_byte == expected_miso) begin
                    $display(" [PASS] %0s: MISO 0x%h", test_name, expected_miso);
                    pass_count = pass_count + 1;
                end else begin
                    $display(
                      " [FAIL] %0s: MISO expected 0x%h, got 0x%h",
                      test_name,
                      expected_miso,
                      miso_captured_byte
                    );
                    fail_count = fail_count + 1;
                end
            end
        end
    endtask

    initial begin
        $dumpfile("dump.vcd");
        $dumpvars(0, tb_spi_bridge_comprehensive);

        rst_n = 0;
        sclk = 0;
        cs_n = 1;
        mosi = 0;
        data_out = 0;
        byte_sync_detected = 0;
        test_count = 0;
        pass_count = 0;
        fail_count = 0;

        #50 rst_n = 1;
        #100;

        $display("========================================");
        $display("=== COMPREHENSIVE SPI BRIDGE TESTS ===");
        $display("========================================");

        // TEST 1: All zeros
        $display("\n--- Test 1: All zeros ---");
        byte_sync_detected = 0;
        data_out = 8'h00;
        send_spi_byte(8'h00, 1, 1);
        wait_for_byte_sync();
        check_result(8'h00, 8'h00, 1, 1, "All zeros");
        #200;

        // TEST 2: All ones
        $display("\n--- Test 2: All ones ---");
        byte_sync_detected = 0;
        data_out = 8'hFF;
        send_spi_byte(8'hFF, 1, 1);
        wait_for_byte_sync();
        check_result(8'hFF, 8'hFF, 1, 1, "All ones");
        #200;

        // TEST 3: Pattern 0xAA
        $display("\n--- Test 3: Pattern 0xAA ---");
        byte_sync_detected = 0;
        data_out = 8'hAA;
        send_spi_byte(8'hAA, 1, 1);
        wait_for_byte_sync();
        check_result(8'hAA, 8'hAA, 1, 1, "Pattern 0xAA");
        #200;

        // TEST 4: Pattern 0x55
        $display("\n--- Test 4: Pattern 0x55 ---");
        byte_sync_detected = 0;
        data_out = 8'h55;
        send_spi_byte(8'h55, 1, 1);
        wait_for_byte_sync();
        check_result(8'h55, 8'h55, 1, 1, "Pattern 0x55");
        #200;

        // TEST 5: Walking 1s
        $display("\n--- Test 5: Walking 1s ---");
        byte_sync_detected = 0;
        data_out = 8'h01;
        send_spi_byte(8'h80, 1, 1);
        wait_for_byte_sync();
        check_result(8'h80, 8'h01, 1, 1, "Walking 1s");
        #200;

        // TEST 6: Full duplex
        $display("\n--- Test 6: Full duplex (TX:0xF0 RX:0x0F) ---");
        byte_sync_detected = 0;
        data_out = 8'hF0;
        send_spi_byte(8'h0F, 1, 1);
        wait_for_byte_sync();
        check_result(8'h0F, 8'hF0, 1, 1, "Full duplex");
        #200;

        // TEST 7: Back-to-back transfers
        $display("\n--- Test 7: Back-to-back transfers ---");
        byte_sync_detected = 0;
        data_out = 8'hDE;
        send_spi_byte(8'hAB, 1, 0);
        wait_for_byte_sync();
        check_result(8'hAB, 8'hDE, 1, 1, "First byte");

        byte_sync_detected = 0;
        data_out = 8'hEF;
        send_spi_byte(8'hCD, 0, 1);
        wait_for_byte_sync();
        check_result(8'hCD, 8'hEF, 1, 1, "Second byte");
        #200;

        // TEST 8: Three consecutive bytes
        $display("\n--- Test 8: Three consecutive bytes ---");
        byte_sync_detected = 0;
        data_out = 8'h11;
        send_spi_byte(8'hAA, 1, 0);
        wait_for_byte_sync();
        check_result(8'hAA, 8'h11, 1, 1, "Byte 1/3");

        byte_sync_detected = 0;
        data_out = 8'h22;
        send_spi_byte(8'hBB, 0, 0);
        wait_for_byte_sync();
        check_result(8'hBB, 8'h22, 1, 1, "Byte 2/3");

        byte_sync_detected = 0;
        data_out = 8'h33;
        send_spi_byte(8'hCC, 0, 1);
        wait_for_byte_sync();
        check_result(8'hCC, 8'h33, 1, 1, "Byte 3/3");
        #200;

        // TEST 9: CS abort
        $display("\n--- Test 9: CS abort at bit 4 ---");
        byte_sync_detected = 0;
        data_out = 8'h99;
        abort_transfer(8'hAB, 4);
        #200;
        if (!byte_sync_detected) begin
            $display(" [PASS] CS abort: No byte_sync");
            test_count = test_count + 1;
            pass_count = pass_count + 1;
        end else begin
            $display(" [FAIL] CS abort: Unexpected byte_sync");
            test_count = test_count + 1;
            fail_count = fail_count + 1;
        end
        #200;

        // TEST 10: byte_sync pulse width
        $display("\n--- Test 10: byte_sync pulse width ---");
        byte_sync_detected = 0;
        data_out = 8'h77;
        send_spi_byte(8'h88, 1, 1);
        wait_for_byte_sync();
        #20;
        if (!byte_sync) begin
            $display(" [PASS] byte_sync is single-cycle");
            test_count = test_count + 1;
            pass_count = pass_count + 1;
        end else begin
            $display(" [FAIL] byte_sync stuck high");
            test_count = test_count + 1;
            fail_count = fail_count + 1;
        end
        #200;

        // TEST 11: Reset during transfer
        $display("\n--- Test 11: Reset during transfer ---");
        byte_sync_detected = 0;
        data_out = 8'h12;
        cs_n = 0;
        #1000;

        mosi = 1; #1000; sclk = 1; #1000; sclk = 0; #1000;
        mosi = 0; #1000; sclk = 1; #1000; sclk = 0; #1000;

        rst_n = 0;
        #500;
        rst_n = 1;
        #2000;

        cs_n = 1;
        if (!byte_sync_detected) begin
            $display(" [PASS] Reset: No spurious byte_sync");
            test_count = test_count + 1;
            pass_count = pass_count + 1;
        end else begin
            $display(" [FAIL] Reset: Unexpected byte_sync");
            test_count = test_count + 1;
            fail_count = fail_count + 1;
        end
        #200;

        // TEST 12: Minimal CS gap
        $display("\n--- Test 12: Minimal CS gap ---");
        byte_sync_detected = 0;
        data_out = 8'h42;
        send_spi_byte(8'h24, 1, 1);
        wait_for_byte_sync();
        check_result(8'h24, 8'h42, 1, 1, "Before gap");

        #20;

        byte_sync_detected = 0;
        data_out = 8'h66;
        send_spi_byte(8'h99, 1, 1);
        wait_for_byte_sync();
        check_result(8'h99, 8'h66, 1, 1, "After gap");
        #200;

        $display("\n========================================");
        $display("=== TEST SUMMARY ===");
        $display("Total: %0d | Passed: %0d | Failed: %0d",
                 test_count, pass_count, fail_count);
        if (fail_count == 0)
            $display("=== ALL TESTS PASSED ===");
        else
            $display("=== %0d TESTS FAILED ===", fail_count);
        $display("========================================");

        $finish;
    end

endmodule

Spi_Bridge/dump.vcd
$date
	Sun Nov 23 23:01:16 2025
$end
$version
	Icarus Verilog
$end
$timescale
	1ps
$end
$scope module tb_spi_bridge_comprehensive $end
$var wire 1 ! miso $end
$var wire 8 " data_in [7:0] $end
$var wire 1 # byte_sync $end
$var reg 1 $ byte_sync_detected $end
$var reg 1 % clk $end
$var reg 1 & cs_n $end
$var reg 8 ' data_in_captured [7:0] $end
$var reg 8 ( data_out [7:0] $end
$var reg 8 ) miso_captured_byte [7:0] $end
$var reg 1 * mosi $end
$var reg 1 + rst_n $end
$var reg 1 , sclk $end
$var integer 32 - fail_count [31:0] $end
$var integer 32 . pass_count [31:0] $end
$var integer 32 / test_count [31:0] $end
$scope module dut $end
$var wire 1 # byte_sync $end
$var wire 1 % clk $end
$var wire 1 & cs_n $end
$var wire 8 0 data_in [7:0] $end
$var wire 8 1 data_out [7:0] $end
$var wire 1 ! miso $end
$var wire 1 * mosi $end
$var wire 1 + rst_n $end
$var wire 1 , sclk $end
$var wire 1 2 sclk_fall $end
$var wire 1 3 sclk_rise $end
$var reg 3 4 bit_cnt [2:0] $end
$var reg 1 5 r_byte_sync $end
$var reg 8 6 r_data_in [7:0] $end
$var reg 1 7 r_miso $end
$var reg 1 8 sclk_prev $end
$var reg 8 9 shift_reg [7:0] $end
$upscope $end
$scope task abort_transfer $end
$var reg 8 : byte_to_send [7:0] $end
$var integer 32 ; abort_at_bit [31:0] $end
$var integer 32 < i [31:0] $end
$upscope $end
$scope task check_result $end
$var reg 1 = check_miso $end
$var reg 1 > check_mosi $end
$var reg 8 ? expected_miso [7:0] $end
$var reg 8 @ expected_mosi [7:0] $end
$var reg 256 A test_name [255:0] $end
$upscope $end
$scope task send_spi_byte $end
$var reg 8 B byte_to_send [7:0] $end
$var reg 1 C end_cs $end
$var reg 1 D start_cs $end
$var integer 32 E i [31:0] $end
$upscope $end
$scope task wait_for_byte_sync $end
$var integer 32 F timeout [31:0] $end
$upscope $end
$upscope $end
$enddefinitions $end
$comment Show the parameter values. $end
$dumpall
$end
#0
$dumpvars
bx F
bx E
xD
xC
bx B
bx A
bx @
bx ?
x>
x=
bx <
bx ;
bx :
b0 9
08
07
b0 6
05
b0 4
03
02
b0 1
b0 0
b0 /
b0 .
b0 -
0,
0+
0*
bx )
b0 (
bx '
1&
0%
0$
0#
b0 "
0!
$end
#50000
1+
1%
#100000
0%
#150000
1%
0&
1C
1D
b0 B
#200000
0%
#250000
1%
#300000
0%
#350000
1%
#400000
0%
#450000
1%
#500000
0%
#550000
1%
#600000
0%
#650000
1%
#700000
0%
#750000
1%
#800000
0%
#850000
1%
#900000
0%
#950000
1%
#1000000
0%
#1050000
1%
#1100000
0%
#1150000
1%
b111 E
b0 )
#1200000
0%
#1250000
1%
#1300000
0%
#1350000
1%
#1400000
0%
#1450000
1%
#1500000
0%
#1550000
1%
#1600000
0%
#1650000
1%
#1700000
0%
#1750000
1%
#1800000
0%
#1850000
1%
#1900000
0%
#1950000
1%
#2000000
0%
#2050000
1%
#2100000
0%
#2150000
b1 4
18
03
1%
1,
#2200000
0%
#2250000
1%
#2300000
0%
#2350000
1%
#2400000
0%
#2450000
1%
#2500000
0%
#2550000
1%
#2600000
0%
#2650000
1%
#2700000
0%
#2750000
1%
#2800000
0%
#2850000
1%
#2900000
0%
#2950000
1%
#3000000
0%
#3050000
1%
#3100000
0%
#3150000
08
02
1%
0,
#3200000
0%
#3250000
1%
#3300000
0%
#3350000
1%
#3400000
0%
#3450000
1%
#3500000
0%
#3550000
1%
#3600000
0%
#3650000
1%
#3700000
0%
#3750000
1%
#3800000
0%
#3850000
1%
#3900000
0%
#3950000
1%
#4000000
0%
#4050000
1%
#4100000
0%
#4150000
1%
b110 E
#4200000
0%
#4250000
1%
#4300000
0%
#4350000
1%
#4400000
0%
#4450000
1%
#4500000
0%
#4550000
1%
#4600000
0%
#4650000
1%
#4700000
0%
#4750000
1%
#4800000
0%
#4850000
1%
#4900000
0%
#4950000
1%
#5000000
0%
#5050000
1%
#5100000
0%
#5150000
b10 4
18
03
1%
1,
#5200000
0%
#5250000
1%
#5300000
0%
#5350000
1%
#5400000
0%
#5450000
1%
#5500000
0%
#5550000
1%
#5600000
0%
#5650000
1%
#5700000
0%
#5750000
1%
#5800000
0%
#5850000
1%
#5900000
0%
#5950000
1%
#6000000
0%
#6050000
1%
#6100000
0%
#6150000
08
02
1%
0,
#6200000
0%
#6250000
1%
#6300000
0%
#6350000
1%
#6400000
0%
#6450000
1%
#6500000
0%
#6550000
1%
#6600000
0%
#6650000
1%
#6700000
0%
#6750000
1%
#6800000
0%
#6850000
1%
#6900000
0%
#6950000
1%
#7000000
0%
#7050000
1%
#7100000
0%
#7150000
1%
b101 E
#7200000
0%
#7250000
1%
#7300000
0%
#7350000
1%
#7400000
0%
#7450000
1%
#7500000
0%
#7550000
1%
#7600000
0%
#7650000
1%
#7700000
0%
#7750000
1%
#7800000
0%
#7850000
1%
#7900000
0%
#7950000
1%
#8000000
0%
#8050000
1%
#8100000
0%
#8150000
b11 4
18
03
1%
1,
#8200000
0%
#8250000
1%
#8300000
0%
#8350000
1%
#8400000
0%
#8450000
1%
#8500000
0%
#8550000
1%
#8600000
0%
#8650000
1%
#8700000
0%
#8750000
1%
#8800000
0%
#8850000
1%
#8900000
0%
#8950000
1%
#9000000
0%
#9050000
1%
#9100000
0%
#9150000
08
02
1%
0,
#9200000
0%
#9250000
1%
#9300000
0%
#9350000
1%
#9400000
0%
#9450000
1%
#9500000
0%
#9550000
1%
#9600000
0%
#9650000
1%
#9700000
0%
#9750000
1%
#9800000
0%
#9850000
1%
#9900000
0%
#9950000
1%
#10000000
0%
#10050000
1%
#10100000
0%
#10150000
1%
b100 E
#10200000
0%
#10250000
1%
#10300000
0%
#10350000
1%
#10400000
0%
#10450000
1%
#10500000
0%
#10550000
1%
#10600000
0%
#10650000
1%
#10700000
0%
#10750000
1%
#10800000
0%
#10850000
1%
#10900000
0%
#10950000
1%
#11000000
0%
#11050000
1%
#11100000
0%
#11150000
b100 4
18
03
1%
1,
#11200000
0%
#11250000
1%
#11300000
0%
#11350000
1%
#11400000
0%
#11450000
1%
#11500000
0%
#11550000
1%
#11600000
0%
#11650000
1%
#11700000
0%
#11750000
1%
#11800000
0%
#11850000
1%
#11900000
0%
#11950000
1%
#12000000
0%
#12050000
1%
#12100000
0%
#12150000
08
02
1%
0,
#12200000
0%
#12250000
1%
#12300000
0%
#12350000
1%
#12400000
0%
#12450000
1%
#12500000
0%
#12550000
1%
#12600000
0%
#12650000
1%
#12700000
0%
#12750000
1%
#12800000
0%
#12850000
1%
#12900000
0%
#12950000
1%
#13000000
0%
#13050000
1%
#13100000
0%
#13150000
1%
b11 E
#13200000
0%
#13250000
1%
#13300000
0%
#13350000
1%
#13400000
0%
#13450000
1%
#13500000
0%
#13550000
1%
#13600000
0%
#13650000
1%
#13700000
0%
#13750000
1%
#13800000
0%
#13850000
1%
#13900000
0%
#13950000
1%
#14000000
0%
#14050000
1%
#14100000
0%
#14150000
b101 4
18
03
1%
1,
#14200000
0%
#14250000
1%
#14300000
0%
#14350000
1%
#14400000
0%
#14450000
1%
#14500000
0%
#14550000
1%
#14600000
0%
#14650000
1%
#14700000
0%
#14750000
1%
#14800000
0%
#14850000
1%
#14900000
0%
#14950000
1%
#15000000
0%
#15050000
1%
#15100000
0%
#15150000
08
02
1%
0,
#15200000
0%
#15250000
1%
#15300000
0%
#15350000
1%
#15400000
0%
#15450000
1%
#15500000
0%
#15550000
1%
#15600000
0%
#15650000
1%
#15700000
0%
#15750000
1%
#15800000
0%
#15850000
1%
#15900000
0%
#15950000
1%
#16000000
0%
#16050000
1%
#16100000
0%
#16150000
1%
b10 E
#16200000
0%
#16250000
1%
#16300000
0%
#16350000
1%
#16400000
0%
#16450000
1%
#16500000
0%
#16550000
1%
#16600000
0%
#16650000
1%
#16700000
0%
#16750000
1%
#16800000
0%
#16850000
1%
#16900000
0%
#16950000
1%
#17000000
0%
#17050000
1%
#17100000
0%
#17150000
b110 4
18
03
1%
1,
#17200000
0%
#17250000
1%
#17300000
0%
#17350000
1%
#17400000
0%
#17450000
1%
#17500000
0%
#17550000
1%
#17600000
0%
#17650000
1%
#17700000
0%
#17750000
1%
#17800000
0%
#17850000
1%
#17900000
0%
#17950000
1%
#18000000
0%
#18050000
1%
#18100000
0%
#18150000
08
02
1%
0,
#18200000
0%
#18250000
1%
#18300000
0%
#18350000
1%
#18400000
0%
#18450000
1%
#18500000
0%
#18550000
1%
#18600000
0%
#18650000
1%
#18700000
0%
#18750000
1%
#18800000
0%
#18850000
1%
#18900000
0%
#18950000
1%
#19000000
0%
#19050000
1%
#19100000
0%
#19150000
1%
b1 E
#19200000
0%
#19250000
1%
#19300000
0%
#19350000
1%
#19400000
0%
#19450000
1%
#19500000
0%
#19550000
1%
#19600000
0%
#19650000
1%
#19700000
0%
#19750000
1%
#19800000
0%
#19850000
1%
#19900000
0%
#19950000
1%
#20000000
0%
#20050000
1%
#20100000
0%
#20150000
b111 4
18
03
1%
1,
#20200000
0%
#20250000
1%
#20300000
0%
#20350000
1%
#20400000
0%
#20450000
1%
#20500000
0%
#20550000
1%
#20600000
0%
#20650000
1%
#20700000
0%
#20750000
1%
#20800000
0%
#20850000
1%
#20900000
0%
#20950000
1%
#21000000
0%
#21050000
1%
#21100000
0%
#21150000
08
02
1%
0,
#21200000
0%
#21250000
1%
#21300000
0%
#21350000
1%
#21400000
0%
#21450000
1%
#21500000
0%
#21550000
1%
#21600000
0%
#21650000
1%
#21700000
0%
#21750000
1%
#21800000
0%
#21850000
1%
#21900000
0%
#21950000
1%
#22000000
0%
#22050000
1%
#22100000
0%
#22150000
1%
b0 E
#22200000
0%
#22250000
1%
#22300000
0%
#22350000
1%
#22400000
0%
#22450000
1%
#22500000
0%
#22550000
1%
#22600000
0%
#22650000
1%
#22700000
0%
#22750000
1%
#22800000
0%
#22850000
1%
#22900000
0%
#22950000
1%
#23000000
0%
#23050000
1%
#23100000
0%
#23150000
1#
15
b0 4
18
03
1%
1,
#23200000
0%
#23250000
0#
05
b0 '
1$
1%
#23300000
0%
#23350000
1%
#23400000
0%
#23450000
1%
#23500000
0%
#23550000
1%
#23600000
0%
#23650000
1%
#23700000
0%
#23750000
1%
#23800000
0%
#23850000
1%
#23900000
0%
#23950000
1%
#24000000
0%
#24050000
1%
#24100000
0%
#24150000
08
02
1%
0,
#24200000
0%
#24250000
1%
#24300000
0%
#24350000
1%
#24400000
0%
#24450000
1%
#24500000
0%
#24550000
1%
#24600000
0%
#24650000
1%
#24700000
0%
#24750000
1%
#24800000
0%
#24850000
1%
#24900000
0%
#24950000
1%
#25000000
0%
#25050000
1%
#25100000
0%
#25150000
1%
b11111111111111111111111111111111 E
#25200000
0%
#25250000
1%
#25300000
0%
#25350000
1%
#25400000
0%
#25450000
1%
#25500000
0%
#25550000
1%
#25600000
0%
#25650000
1%
#25700000
0%
#25750000
1%
#25800000
0%
#25850000
1%
#25900000
0%
#25950000
1%
#26000000
0%
#26050000
1%
#26100000
0%
#26150000
1%
1&
#26200000
0%
#26250000
1%
#26300000
0%
#26350000
1%
#26400000
0%
#26450000
1%
#26500000
0%
#26550000
1%
#26600000
0%
#26650000
1%
#26700000
0%
#26750000
1%
#26800000
0%
#26850000
1%
#26900000
0%
#26950000
1%
#27000000
0%
#27050000
1%
#27100000
0%
#27150000
1%
b10 .
b1 /
b10000010110110001101100001000000111101001100101011100100110111101110011 A
1=
1>
b0 ?
b0 @
b0 F
#27200000
0%
#27250000
1%
#27300000
0%
#27350000
1!
17
1%
0&
b11111111 B
b11111111 (
b11111111 1
0$
#27400000
0%
#27450000
1%
#27500000
0%
#27550000
1%
#27600000
0%
#27650000
1%
#27700000
0%
#27750000
1%
#27800000
0%
#27850000
1%
#27900000
0%
#27950000
1%
#28000000
0%
#28050000
1%
#28100000
0%
#28150000
1%
#28200000
0%
#28250000
1%
#28300000
0%
#28350000
1%
1*
b111 E
#28400000
0%
#28450000
1%
#28500000
0%
#28550000
1%
#28600000
0%
#28650000
1%
#28700000
0%
#28750000
1%
#28800000
0%
#28850000
1%
#28900000
0%
#28950000
1%
#29000000
0%
#29050000
1%
#29100000
0%
#29150000
1%
#29200000
0%
#29250000
1%
#29300000
0%
#29350000
b1 4
b1 9
18
03
1%
1,
#29400000
0%
#29450000
1%
#29500000
0%
#29550000
1%
#29600000
0%
#29650000
1%
#29700000
0%
#29750000
1%
#29800000
0%
#29850000
1%
b10000000 )
#29900000
0%
#29950000
1%
#30000000
0%
#30050000
1%
#30100000
0%
#30150000
1%
#30200000
0%
#30250000
1%
#30300000
0%
#30350000
08
02
1%
0,
#30400000
0%
#30450000
1%
#30500000
0%
#30550000
1%
#30600000
0%
#30650000
1%
#30700000
0%
#30750000
1%
#30800000
0%
#30850000
1%
#30900000
0%
#30950000
1%
#31000000
0%
#31050000
1%
#31100000
0%
#31150000
1%
#31200000
0%
#31250000
1%
#31300000
0%
#31350000
1%
b110 E
#31400000
0%
#31450000
1%
#31500000
0%
#31550000
1%
#31600000
0%
#31650000
1%
#31700000
0%
#31750000
1%
#31800000
0%
#31850000
1%
#31900000
0%
#31950000
1%
#32000000
0%
#32050000
1%
#32100000
0%
#32150000
1%
#32200000
0%
#32250000
1%
#32300000
0%
#32350000
b10 4
b11 9
18
03
1%
1,
#32400000
0%
#32450000
1%
#32500000
0%
#32550000
1%
#32600000
0%
#32650000
1%
#32700000
0%
#32750000
1%
#32800000
0%
#32850000
1%
b11000000 )
#32900000
0%
#32950000
1%
#33000000
0%
#33050000
1%
#33100000
0%
#33150000
1%
#33200000
0%
#33250000
1%
#33300000
0%
#33350000
08
02
1%
0,
#33400000
0%
#33450000
1%
#33500000
0%
#33550000
1%
#33600000
0%
#33650000
1%
#33700000
0%
#33750000
1%
#33800000
0%
#33850000
1%
#33900000
0%
#33950000
1%
#34000000
0%
#34050000
1%
#34100000
0%
#34150000
1%
#34200000
0%
#34250000
1%
#34300000
0%
#34350000
1%
b101 E
#34400000
0%
#34450000
1%
#34500000
0%
#34550000
1%
#34600000
0%
#34650000
1%
#34700000
0%
#34750000
1%
#34800000
0%
#34850000
1%
#34900000
0%
#34950000
1%
#35000000
0%
#35050000
1%
#35100000
0%
#35150000
1%
#35200000
0%
#35250000
1%
#35300000
0%
#35350000
b11 4
b111 9
18
03
1%
1,
#35400000
0%
#35450000
1%
#35500000
0%
#35550000
1%
#35600000
0%
#35650000
1%
#35700000
0%
#35750000
1%
#35800000
0%
#35850000
1%
b11100000 )
#35900000
0%
#35950000
1%
#36000000
0%
#36050000
1%
#36100000
0%
#36150000
1%
#36200000
0%
#36250000
1%
#36300000
0%
#36350000
08
02
1%
0,
#36400000
0%
#36450000
1%
#36500000
0%
#36550000
1%
#36600000
0%
#36650000
1%
#36700000
0%
#36750000
1%
#36800000
0%
#36850000
1%
#36900000
0%
#36950000
1%
#37000000
0%
#37050000
1%
#37100000
0%
#37150000
1%
#37200000
0%
#37250000
1%
#37300000
0%
#37350000
1%
b100 E
#37400000
0%
#37450000
1%
#37500000
0%
#37550000
1%
#37600000
0%
#37650000
1%
#37700000
0%
#37750000
1%
#37800000
0%
#37850000
1%
#37900000
0%
#37950000
1%
#38000000
0%
#38050000
1%
#38100000
0%
#38150000
1%
#38200000
0%
#38250000
1%
#38300000
0%
#38350000
b100 4
b1111 9
18
03
1%
1,
#38400000
0%
#38450000
1%
#38500000
0%
#38550000
1%
#38600000
0%
#38650000
1%
#38700000
0%
#38750000
1%
#38800000
0%
#38850000
1%
b11110000 )
#38900000
0%
#38950000
1%
#39000000
0%
#39050000
1%
#39100000
0%
#39150000
1%
#39200000
0%
#39250000
1%
#39300000
0%
#39350000
08
02
1%
0,
#39400000
0%
#39450000
1%
#39500000
0%
#39550000
1%
#39600000
0%
#39650000
1%
#39700000
0%
#39750000
1%
#39800000
0%
#39850000
1%
#39900000
0%
#39950000
1%
#40000000
0%
#40050000
1%
#40100000
0%
#40150000
1%
#40200000
0%
#40250000
1%
#40300000
0%
#40350000
1%
b11 E
#40400000
0%
#40450000
1%
#40500000
0%
#40550000
1%
#40600000
0%
#40650000
1%
#40700000
0%
#40750000
1%
#40800000
0%
#40850000
1%
#40900000
0%
#40950000
1%
#41000000
0%
#41050000
1%
#41100000
0%
#41150000
1%
#41200000
0%
#41250000
1%
#41300000
0%
#41350000
b101 4
b11111 9
18
03
1%
1,
#41400000
0%
#41450000
1%
#41500000
0%
#41550000
1%
#41600000
0%
#41650000
1%
#41700000
0%
#41750000
1%
#41800000
0%
#41850000
1%
b11111000 )
#41900000
0%
#41950000
1%
#42000000
0%
#42050000
1%
#42100000
0%
#42150000
1%
#42200000
0%
#42250000
1%
#42300000
0%
#42350000
08
02
1%
0,
#42400000
0%
#42450000
1%
#42500000
0%
#42550000
1%
#42600000
0%
#42650000
1%
#42700000
0%
#42750000
1%
#42800000
0%
#42850000
1%
#42900000
0%
#42950000
1%
#43000000
0%
#43050000
1%
#43100000
0%
#43150000
1%
#43200000
0%
#43250000
1%
#43300000
0%
#43350000
1%
b10 E
#43400000
0%
#43450000
1%
#43500000
0%
#43550000
1%
#43600000
0%
#43650000
1%
#43700000
0%
#43750000
1%
#43800000
0%
#43850000
1%
#43900000
0%
#43950000
1%
#44000000
0%
#44050000
1%
#44100000
0%
#44150000
1%
#44200000
0%
#44250000
1%
#44300000
0%
#44350000
b110 4
b111111 9
18
03
1%
1,
#44400000
0%
#44450000
1%
#44500000
0%
#44550000
1%
#44600000
0%
#44650000
1%
#44700000
0%
#44750000
1%
#44800000
0%
#44850000
1%
b11111100 )
#44900000
0%
#44950000
1%
#45000000
0%
#45050000
1%
#45100000
0%
#45150000
1%
#45200000
0%
#45250000
1%
#45300000
0%
#45350000
08
02
1%
0,
#45400000
0%
#45450000
1%
#45500000
0%
#45550000
1%
#45600000
0%
#45650000
1%
#45700000
0%
#45750000
1%
#45800000
0%
#45850000
1%
#45900000
0%
#45950000
1%
#46000000
0%
#46050000
1%
#46100000
0%
#46150000
1%
#46200000
0%
#46250000
1%
#46300000
0%
#46350000
1%
b1 E
#46400000
0%
#46450000
1%
#46500000
0%
#46550000
1%
#46600000
0%
#46650000
1%
#46700000
0%
#46750000
1%
#46800000
0%
#46850000
1%
#46900000
0%
#46950000
1%
#47000000
0%
#47050000
1%
#47100000
0%
#47150000
1%
#47200000
0%
#47250000
1%
#47300000
0%
#47350000
b111 4
b1111111 9
18
03
1%
1,
#47400000
0%
#47450000
1%
#47500000
0%
#47550000
1%
#47600000
0%
#47650000
1%
#47700000
0%
#47750000
1%
#47800000
0%
#47850000
1%
b11111110 )
#47900000
0%
#47950000
1%
#48000000
0%
#48050000
1%
#48100000
0%
#48150000
1%
#48200000
0%
#48250000
1%
#48300000
0%
#48350000
08
02
1%
0,
#48400000
0%
#48450000
1%
#48500000
0%
#48550000
1%
#48600000
0%
#48650000
1%
#48700000
0%
#48750000
1%
#48800000
0%
#48850000
1%
#48900000
0%
