Counter/counter.v
module counter (
    // peripheral clock signals
    input clk,
    input rst_n,

    // register-facing signals
    output reg [15:0] count_val,
    input [15:0] period,
    input en,
    input count_reset,
    input upnotdown,
    input [7:0] prescale
);

    // internal prescaler counter
    // prescale_cnt counts from 0 to prescale
    reg [7:0] prescale_cnt;

    always @(posedge clk or negedge rst_n) begin
        if (!rst_n) begin
            // full asynchronous reset
            count_val    <= 16'd0;
            prescale_cnt <= 8'd0;

        end else begin

            // counter_reset only resets the counter,
            // does NOT reset other peripheral registers.
            if (count_reset) begin
                count_val    <= 16'd0;
                prescale_cnt <= 8'd0;
            end 

            // counter logic only when enabled
            else if (en) begin

                // prescaler reached → perform one increment/decrement
                if (prescale_cnt == prescale) begin
                    prescale_cnt <= 0;

                    // counting direction
                    if (upnotdown) begin
                        // count up
                        if (count_val == period)
                            count_val <= 16'd0;       // OVERFLOW → wrap
                        else
                            count_val <= count_val + 1;

                    end else begin
                        // count down
                        if (count_val == 0)
                            count_val <= period;      // UNDERFLOW → wrap
                        else
                            count_val <= count_val - 1;
                    end
                end

                // prescaler has not expired → keep counting internal cycles
                else begin
                    prescale_cnt <= prescale_cnt + 1;
                end

            end 
            // if en == 0 → counter is frozen (keeps its value)
        end
    end

endmodule

Counter/tb_counter.v
`timescale 1ns/1ps

module tb_counter;

    // ============================
    // DUT Inputs
    // ============================
    reg clk;
    reg rst_n;
    reg en;
    reg upnotdown;
    reg count_reset;
    reg [7:0] prescale;
    reg [15:0] period;

    // DUT Output
    wire [15:0] count_val;

    // ============================
    // Instantiate DUT
    // ============================
    counter dut (
        .clk(clk),
        .rst_n(rst_n),
        .count_val(count_val),
        .period(period),
        .en(en),
        .count_reset(count_reset),
        .upnotdown(upnotdown),
        .prescale(prescale)
    );

    // ============================
    // Clock
    // ============================
    initial clk = 0;
    always #5 clk = ~clk;

    // ============================
    // HELPER TASKS (IVerilog-safe)
    // ============================

    task step;
        input integer n;
        integer i;
        begin
            for (i=0; i<n; i=i+1)
                @(posedge clk);
        end
    endtask

    task assert_equal;
        input [15:0] got;
        input [15:0] expected;
        begin
            if (got !== expected) begin
                $display("❌ ASSERT FAILED at t=%0t : got %0d expected %0d",
                        $time, got, expected);
                $finish;
            end
        end
    endtask

    task show;
        begin
            $display("[%0t] CNT=%0d  en=%b  up=%b  pres=%0d  per=%0d",
                    $time, count_val, en, upnotdown, prescale, period);
        end
    endtask

    // ============================
    // BEGIN TESTS
    // ============================
    integer i;
    integer cycles_before;
    integer cycle_cnt;

    initial begin
        $dumpfile("counter_full_tb.vcd");
        $dumpvars(0, tb_counter);

        // default
        rst_n = 0;
        en = 0;
        upnotdown = 1;
        count_reset = 0;
        prescale = 0;
        period = 10;

        step(3);
        rst_n = 1;
        step(1);

        // ===========================================================
        // TEST 1 — RESET
        // ===========================================================
        $display("\n=== TEST 1 — RESET ===");
        assert_equal(count_val, 0);

        // ===========================================================
        // TEST 2 — SIMPLE UP COUNT
        // ===========================================================
        $display("\n=== TEST 2 — SIMPLE COUNT UP ===");
        en = 1;
        upnotdown = 1;
        prescale = 0;

        while (count_val != period)
            step(1);

        step(1);
        assert_equal(count_val, 0);

        // ===========================================================
        // TEST 3 — COUNT DOWN
        // ===========================================================
        $display("\n=== TEST 3 — COUNT DOWN ===");
        upnotdown = 0;

        step(1);
        assert_equal(count_val, period);

        while (count_val != 0)
            step(1);

        step(1);
        assert_equal(count_val, period);

        // ===========================================================
        // TEST 4 — PRESCALE
        // ===========================================================
        $display("\n=== TEST 4 — PRESCALE ===");
        prescale = 5;
        count_reset = 1; step(1); count_reset = 0;

        cycles_before = count_val;
        cycle_cnt = 0;

        while (count_val == cycles_before) begin
            step(1);
            cycle_cnt = cycle_cnt + 1;
        end

        assert_equal(cycle_cnt, prescale + 1);

       // ===========================================================
// TEST 5 — FREEZE (en=0)
// ===========================================================
$display("\n=== TEST 5 — FREEZE (en=0) ===");

// 1) Reset complet pentru stare stabilă
rst_n = 0; step(1);
rst_n = 1; step(2);

// 2) Setări de test
prescale    = 5;
period      = 10;
upnotdown   = 1;
en          = 1;

// 3) Las counterul să avanseze puțin
step(20);

// 4) Salvez valoarea înainte de înghețare
cycles_before = count_val;

// 5) Dezactivez counterul (FREEZE)
en = 0;

// 6) Aștept MULT → trebuie să rămână înghețat
step(30);
assert_equal(count_val, cycles_before);

// 7) Repornește counterul
en = 1;

// 8) Așteaptă suficient cât să termine prescalerul
step(prescale + 2);

// 9) Verificare logică
if (cycles_before == period)
    assert_equal(count_val, 0);
else
    assert_equal(count_val, cycles_before + 1);

        // ===========================================================
        // TEST 6 — COUNT_RESET
        // ===========================================================
        $display("\n=== TEST 6 — COUNT_RESET ===");
        count_reset = 1; step(1); count_reset = 0;
        assert_equal(count_val, 0);

        // ===========================================================
        // TEST 7 — CHANGE PERIOD MID-RUN
        // ===========================================================
        $display("\n=== TEST 7 — CHANGE PERIOD MID-RUN ===");
        period = 4;
        prescale = 0;
        upnotdown = 1;
        count_reset = 1; step(1); count_reset = 0;

        step(4);
        assert_equal(count_val, 4);

        step(1);
        assert_equal(count_val, 0);

        // ===========================================================
        // TEST 8 — DIRECTION FLIP MID RUN
        // ===========================================================
        $display("\n=== TEST 8 — DIRECTION FLIP ===");
        period = 10;
        count_reset = 1; step(1); count_reset = 0;
        prescale = 0;
        upnotdown = 1;

        step(1);
        cycles_before = count_val;

        upnotdown = 0;

        step(1);

        if (cycles_before == 0)
            assert_equal(count_val, period);
        else
            assert_equal(count_val, cycles_before - 1);

        // ===========================================================
        // TEST 9 — LARGE PRESCALE
        // ===========================================================
        $display("\n=== TEST 9 — LARGE PRESCALE ===");
        prescale = 20;
        count_reset = 1; step(1); count_reset = 0;

        cycles_before = count_val;
        cycle_cnt = 0;

        while (count_val == cycles_before) begin
            step(1);
            cycle_cnt = cycle_cnt + 1;
        end

        assert_equal(cycle_cnt, prescale + 1);

        // ===========================================================
        // TEST 10 — PERIOD = 0
        // ===========================================================
        $display("\n=== TEST 10 — PERIOD = 0 EDGE CASE ===");
        period = 0;
        prescale = 0;
        upnotdown = 1;

        count_reset = 1; step(1); count_reset = 0;

        step(20);
        assert_equal(count_val, 0);

        // ===========================================================
        // TEST 11 — RANDOM STRESS TEST
        // ===========================================================
        $display("\n=== TEST 11 — RANDOM STRESS TEST ===");

        period = 20;
        prescale = 0;
        upnotdown = 1;
        count_reset = 1; step(1); count_reset = 0;

        for (i=0; i<200; i=i+1) begin
            step($urandom_range(1,4));

            if ($urandom % 7 == 0)
                period = $urandom_range(0,20);

            if ($urandom % 11 == 0)
                upnotdown = ~upnotdown;

            if ($urandom % 13 == 0)
                prescale = $urandom_range(0,10);

            if ($urandom % 17 == 0)
                en = ~en;

            if ($urandom % 19 == 0) begin
                count_reset = 1; step(1); count_reset = 0;
            end
        end

        $display("\n==============================================");
        $display("         ALL COUNTER TESTS PASSED");
        $display("==============================================\n");

        $finish;
    end

endmodule

Counter/counter_full_tb.vcd
$date
	Sun Nov 23 23:26:46 2025
$end
$version
	Icarus Verilog
$end
$timescale
	1ps
$end
$scope module tb_counter $end
$var wire 16 ! count_val [15:0] $end
$var reg 1 " clk $end
$var reg 1 # count_reset $end
$var reg 1 $ en $end
$var reg 16 % period [15:0] $end
$var reg 8 & prescale [7:0] $end
$var reg 1 ' rst_n $end
$var reg 1 ( upnotdown $end
$var integer 32 ) cycle_cnt [31:0] $end
$var integer 32 * cycles_before [31:0] $end
$var integer 32 + i [31:0] $end
$scope module dut $end
$var wire 1 " clk $end
$var wire 1 # count_reset $end
$var wire 1 $ en $end
$var wire 16 , period [15:0] $end
$var wire 8 - prescale [7:0] $end
$var wire 1 ' rst_n $end
$var wire 1 ( upnotdown $end
$var reg 16 . count_val [15:0] $end
$var reg 8 / prescale_cnt [7:0] $end
$upscope $end
$scope task assert_equal $end
$var reg 16 0 expected [15:0] $end
$var reg 16 1 got [15:0] $end
$upscope $end
$scope task show $end
$upscope $end
$scope task step $end
$var integer 32 2 i [31:0] $end
$var integer 32 3 n [31:0] $end
$upscope $end
$upscope $end
$enddefinitions $end
$comment Show the parameter values. $end
$dumpall
$end
#0
$dumpvars
b11 3
b0 2
bx 1
bx 0
b0 /
b0 .
b0 -
b1010 ,
bx +
bx *
bx )
1(
0'
b0 &
b1010 %
0$
0#
0"
b0 !
$end
#5000
b1 2
1"
#10000
0"
#15000
b10 2
1"
#20000
0"
#25000
b1 3
1'
b0 2
1"
#30000
0"
#35000
b1 !
b1 .
1$
b0 0
b0 1
b0 2
1"
#40000
0"
#45000
b10 !
b10 .
b0 2
1"
#50000
0"
#55000
b11 !
b11 .
b0 2
1"
#60000
0"
#65000
b100 !
b100 .
b0 2
1"
#70000
0"
#75000
b101 !
b101 .
b0 2
1"
#80000
0"
#85000
b110 !
b110 .
b0 2
1"
#90000
0"
#95000
b111 !
b111 .
b0 2
1"
#100000
0"
#105000
b1000 !
b1000 .
b0 2
1"
#110000
0"
#115000
b1001 !
b1001 .
b0 2
1"
#120000
0"
#125000
b1010 !
b1010 .
b0 2
1"
#130000
0"
#135000
b0 !
b0 .
b0 2
1"
#140000
0"
#145000
b1010 !
b1010 .
0(
b0 2
1"
#150000
0"
#155000
b1001 !
b1001 .
b1010 0
b1010 1
b0 2
1"
#160000
0"
#165000
b1000 !
b1000 .
b0 2
1"
#170000
0"
#175000
b111 !
b111 .
b0 2
1"
#180000
0"
#185000
b110 !
b110 .
b0 2
1"
#190000
0"
#195000
b101 !
b101 .
b0 2
1"
#200000
0"
#205000
b100 !
b100 .
b0 2
1"
#210000
0"
#215000
b11 !
b11 .
b0 2
1"
#220000
0"
#225000
b10 !
b10 .
b0 2
1"
#230000
0"
#235000
b1 !
b1 .
b0 2
1"
#240000
0"
#245000
b0 !
b0 .
b0 2
1"
#250000
0"
#255000
b1010 !
b1010 .
b0 2
1"
#260000
0"
#265000
b0 !
b0 .
1#
b101 &
b101 -
b0 2
1"
#270000
0"
#275000
b1 /
b0 )
b0 *
0#
b0 2
1"
#280000
0"
#285000
b10 /
b1 )
b0 2
1"
#290000
0"
#295000
b11 /
b10 )
b0 2
1"
#300000
0"
#305000
b100 /
b11 )
b0 2
1"
#310000
0"
#315000
b101 /
b100 )
b0 2
1"
#320000
0"
#325000
b1010 !
b1010 .
b0 /
b101 )
b0 2
1"
#330000
0"
#335000
b0 !
b0 .
0'
b110 0
b110 1
b110 )
b0 2
1"
#340000
0"
#345000
b1 /
b10 3
1'
b0 2
1"
#350000
0"
#355000
b10 /
b1 2
1"
#360000
0"
#365000
b11 /
b10100 3
1(
b0 2
1"
#370000
0"
#375000
b100 /
b1 2
1"
#380000
0"
#385000
b101 /
b10 2
1"
#390000
0"
#395000
b1 !
b1 .
b0 /
b11 2
1"
#400000
0"
#405000
b1 /
b100 2
1"
#410000
0"
#415000
b10 /
b101 2
1"
#420000
0"
#425000
b11 /
b110 2
1"
#430000
0"
#435000
b100 /
b111 2
1"
#440000
0"
#445000
b101 /
b1000 2
1"
#450000
0"
#455000
b10 !
b10 .
b0 /
b1001 2
1"
#460000
0"
#465000
b1 /
b1010 2
1"
#470000
0"
#475000
b10 /
b1011 2
1"
#480000
0"
#485000
b11 /
b1100 2
1"
#490000
0"
#495000
b100 /
b1101 2
1"
#500000
0"
#505000
b101 /
b1110 2
1"
#510000
0"
#515000
b11 !
b11 .
b0 /
b1111 2
1"
#520000
0"
#525000
b1 /
b10000 2
1"
#530000
0"
#535000
b10 /
b10001 2
1"
#540000
0"
#545000
b11 /
b10010 2
1"
#550000
0"
#555000
b100 /
b10011 2
1"
#560000
0"
#565000
b11110 3
0$
b11 *
b0 2
1"
#570000
0"
#575000
b1 2
1"
#580000
0"
#585000
b10 2
1"
#590000
0"
#595000
b11 2
1"
#600000
0"
#605000
b100 2
1"
#610000
0"
#615000
b101 2
1"
#620000
0"
#625000
b110 2
1"
#630000
0"
#635000
b111 2
1"
#640000
0"
#645000
b1000 2
1"
#650000
0"
#655000
b1001 2
1"
#660000
0"
#665000
b1010 2
1"
#670000
0"
#675000
b1011 2
1"
#680000
0"
#685000
b1100 2
1"
#690000
0"
#695000
b1101 2
1"
#700000
0"
#705000
b1110 2
1"
#710000
0"
#715000
b1111 2
1"
#720000
0"
#725000
b10000 2
1"
#730000
0"
#735000
b10001 2
1"
#740000
0"
#745000
b10010 2
1"
#750000
0"
#755000
b10011 2
1"
#760000
0"
#765000
b10100 2
1"
#770000
0"
#775000
b10101 2
1"
#780000
0"
#785000
b10110 2
1"
#790000
0"
#795000
b10111 2
1"
#800000
0"
#805000
b11000 2
1"
#810000
0"
#815000
b11001 2
1"
#820000
0"
#825000
b11010 2
1"
#830000
0"
#835000
b11011 2
1"
#840000
0"
#845000
b11100 2
1"
#850000
0"
#855000
b11101 2
1"
#860000
0"
#865000
b101 /
b111 3
1$
b11 0
b11 1
b0 2
1"
#870000
0"
#875000
b100 !
b100 .
b0 /
b1 2
1"
#880000
0"
#885000
b1 /
b10 2
1"
#890000
0"
#895000
b10 /
b11 2
1"
#900000
0"
#905000
b11 /
b100 2
1"
#910000
0"
#915000
b100 /
b101 2
1"
#920000
0"
#925000
b101 /
b110 2
1"
#930000
0"
#935000
b0 /
b0 !
b0 .
b1 3
1#
b100 0
b100 1
b0 2
1"
#940000
0"
#945000
b0 &
b0 -
b100 %
b100 ,
b0 0
b0 1
1#
b0 2
1"
#950000
0"
#955000
b1 !
b1 .
b100 3
0#
b0 2
1"
#960000
0"
#965000
b10 !
b10 .
b1 2
1"
#970000
0"
#975000
b11 !
b11 .
b10 2
1"
#980000
0"
#985000
b100 !
b100 .
b11 2
1"
#990000
0"
#995000
b0 !
b0 .
b1 3
b100 0
b100 1
b0 2
1"
#1000000
0"
#1005000
1#
b1010 %
b1010 ,
b0 0
b0 1
b0 2
1"
#1010000
0"
#1015000
b1 !
b1 .
0#
b0 2
1"
#1020000
0"
#1025000
b0 !
b0 .
0(
b1 *
b0 2
1"
#1030000
0"
#1035000
1#
b10100 &
b10100 -
b0 2
1"
#1040000
0"
#1045000
b1 /
b0 )
b0 *
0#
b0 2
1"
#1050000
0"
#1055000
b10 /
b1 )
b0 2
1"
#1060000
0"
#1065000
b11 /
b10 )
b0 2
1"
#1070000
0"
#1075000
b100 /
b11 )
b0 2
1"
#1080000
0"
#1085000
b101 /
b100 )
b0 2
1"
#1090000
0"
#1095000
b110 /
b101 )
b0 2
1"
#1100000
0"
#1105000
b111 /
b110 )
b0 2
1"
#1110000
0"
#1115000
b1000 /
b111 )
b0 2
1"
#1120000
0"
#1125000
b1001 /
b1000 )
b0 2
1"
#1130000
0"
#1135000
b1010 /
b1001 )
b0 2
1"
#1140000
0"
#1145000
b1011 /
b1010 )
b0 2
1"
#1150000
0"
#1155000
b1100 /
b1011 )
b0 2
1"
#1160000
0"
#1165000
b1101 /
b1100 )
b0 2
1"
#1170000
0"
#1175000
b1110 /
b1101 )
b0 2
1"
#1180000
0"
#1185000
b1111 /
b1110 )
b0 2
1"
#1190000
0"
#1195000
b10000 /
b1111 )
b0 2
1"
#1200000
0"
#1205000
b10001 /
b10000 )
b0 2
1"
#1210000
0"
#1215000
b10010 /
b10001 )
b0 2
1"
#1220000
0"
#1225000
b10011 /
b10010 )
b0 2
1"
#1230000
0"
#1235000
b10100 /
b10011 )
b0 2
1"
#1240000
0"
#1245000
b1010 !
b1010 .
b0 /
b10100 )
b0 2
1"
#1250000
0"
#1255000
b0 !
b0 .
1#
1(
b0 &
b0 -
b0 %
b0 ,
b10101 0
b10101 1
b10101 )
b0 2
1"
#1260000
0"
#1265000
b10100 3
0#
b0 2
1"
#1270000
0"
#1275000
b1 2
1"
#1280000
0"
#1285000
b10 2
1"
#1290000
0"
#1295000
b11 2
1"
#1300000
0"
#1305000
b100 2
1"
#1310000
0"
#1315000
b101 2
1"
#1320000
0"
#1325000
b110 2
1"
#1330000
0"
#1335000
b111 2
1"
#1340000
0"
#1345000
b1000 2
1"
#1350000
0"
#1355000
b1001 2
1"
#1360000
0"
#1365000
b1010 2
1"
#1370000
0"
#1375000
b1011 2
1"
#1380000
0"
#1385000
b1100 2
1"
#1390000
0"
#1395000
b1101 2
1"
#1400000
0"
#1405000
b1110 2
1"
#1410000
0"
#1415000
b1111 2
1"
#1420000
0"
#1425000
b10000 2
1"
#1430000
0"
#1435000
b10001 2
1"
#1440000
0"
#1445000
b10010 2
1"
#1450000
0"
#1455000
b10011 2
1"
#1460000
0"
#1465000
b1 3
1#
b10100 %
b10100 ,
b0 0
b0 1
b0 2
1"
#1470000
0"
#1475000
b1 !
b1 .
b11 3
b0 +
0#
b0 2
1"
#1480000
0"
#1485000
b10 !
b10 .
b1 2
1"
#1490000
0"
#1495000
b11 !
b11 .
b10 2
1"
#1500000
0"
#1505000
b10 !
b10 .
b1 3
b1 +
0(
b0 2
1"
#1510000
0"
#1515000
b11 !
b11 .
b100 3
b10 +
1(
b0 2
1"
#1520000
0"
#1525000
b100 !
b100 .
b1 2
1"
#1530000
0"
#1535000
b101 !
b101 .
b10 2
1"
#1540000
0"
#1545000
b110 !
b110 .
b11 2
1"
#1550000
0"
#1555000
b111 !
b111 .
b11 +
b0 2
1"
#1560000
0"
#1565000
b1000 !
b1000 .
b1 2
1"
#1570000
0"
#1575000
b1001 !
b1001 .
b10 2
1"
#1580000
0"
#1585000
b1010 !
b1010 .
b11 2
1"
#1590000
0"
#1595000
b1001 !
b1001 .
b10 3
b100 +
0(
b0 2
1"
#1600000
0"
#1605000
b1000 !
b1000 .
b1 2
1"
#1610000
0"
#1615000
b111 !
b111 .
b1 3
b101 +
b0 2
1"
#1620000
0"
#1625000
b110 !
b110 .
b10 3
b110 +
b0 2
1"
#1630000
0"
#1635000
b101 !
b101 .
b1 2
1"
#1640000
0"
#1645000
b110 !
b110 .
b1 3
b111 +
1(
b0 2
1"
#1650000
0"
#1655000
b111 !
b111 .
b10 3
b1000 +
b0 2
1"
#1660000
0"
#1665000
b1000 !
b1000 .
b1 2
1"
#1670000
0"
#1675000
b1001 !
b1001 .
b11 3
b1001 +
b0 2
1"
#1680000
0"
#1685000
b1010 !
b1010 .
b1 2
1"
#1690000
0"
#1695000
b1011 !
b1011 .
b10 2
1"
#1700000
0"
#1705000
b1100 !
b1100 .
b1010 +
b0 2
1"
#1710000
0"
#1715000
b1101 !
b1101 .
b1 2
1"
#1720000
0"
#1725000
b1110 !
b1110 .
b10 2
1"
#1730000
0"
#1735000
b1 /
b1 3
b1011 +
b111 &
b111 -
b0 2
1"
#1740000
0"
#1745000
b0 /
b0 !
b0 .
1#
b0 2
1"
#1750000
0"
#1755000
b1 /
b100 3
b1100 +
0#
b0 2
1"
#1760000
0"
#1765000
b10 /
b1 2
1"
#1770000
0"
#1775000
b11 /
b10 2
1"
#1780000
0"
#1785000
b100 /
b11 2
1"
#1790000
0"
#1795000
b101 /
b1 3
b1101 +
b0 2
1"
#1800000
0"
#1805000
b110 /
b11 3
b1110 +
b100 &
b100 -
0(
b0 2
1"
#1810000
0"
#1815000
b111 /
b1 2
1"
#1820000
0"
#1825000
b1000 /
b10 2
1"
#1830000
0"
#1835000
b1001 /
b1111 +
b110 &
b110 -
b0 2
1"
#1840000
0"
#1845000
b1010 /
b1 2
1"
#1850000
0"
#1855000
b1011 /
b10 2
1"
#1860000
0"
#1865000
b1100 /
b10000 +
b0 2
1"
#1870000
0"
#1875000
b1101 /
b1 2
1"
#1880000
0"
#1885000
b1110 /
b10 2
1"
#1890000
0"
#1895000
b1111 /
b10 3
b10001 +
b0 2
1"
#1900000
0"
#1905000
b10000 /
b1 2
1"
#1910000
0"
#1915000
b10001 /
b1 3
b10010 +
b0 2
1"
#1920000
0"
#1925000
b10010 /
b10 3
b10011 +
b0 2
1"
#1930000
0"
#1935000
b10011 /
b1 2
1"
#1940000
0"
#1945000
b10100 /
b10100 +
1(
b0 2
1"
#1950000
0"
#1955000
b10101 /
b1 2
1"
#1960000
0"
#1965000
b10110 /
b100 3
b10101 +
b0 2
1"
#1970000
0"
#1975000
b10111 /
b1 2
1"
#1980000
0"
#1985000
b11000 /
b10 2
1"
#1990000
0"
#1995000
b11001 /
b11 2
1"
#2000000
0"
#2005000
b11010 /
b11 3
b10110 +
b0 2
1"
#2010000
0"
#2015000
b11011 /
b1 2
1"
#2020000
0"
#2025000
b11100 /
b10 2
1"
#2030000
0"
#2035000
b10111 +
0$
b0 2
1"
#2040000
0"
#2045000
b1 2
1"
#2050000
0"
#2055000
b10 2
1"
#2060000
0"
#2065000
b100 3
b11000 +
b0 2
1"
#2070000
0"
#2075000
b1 2
1"
#2080000
0"
#2085000
b10 2
1"
#2090000
0"
#2095000
b11 2
1"
#2100000
0"
#2105000
b11001 +
b0 2
1"
#2110000
0"
#2115000
b1 2
1"
#2120000
0"
#2125000
b10 2
1"
#2130000
0"
#2135000
b11 2
1"
#2140000
0"
#2145000
b10 3
b11010 +
b0 2
1"
#2150000
0"
#2155000
b1 2
1"
#2160000
0"
#2165000
b0 /
b1 3
1#
b0 2
1"
#2170000
0"
#2175000
b11011 +
0#
b0 2
1"
#2180000
0"
#2185000
b10 3
b11100 +
b0 2
1"
#2190000
0"
#2195000
b1 2
1"
#2200000
0"
#2205000
b11 3
b11101 +
0(
b0 2
1"
#2210000
0"
#2215000
b1 2
1"
#2220000
0"
#2225000
b10 2
1"
#2230000
0"
#2235000
b100 3
b11110 +
b0 2
1"
#2240000
0"
#2245000
b1 2
1"
#2250000
0"
#2255000
b10 2
1"
#2260000
0"
#2265000
b11 2
1"
#2270000
0"
#2275000
b11111 +
b0 2
1"
#2280000
0"
#2285000
b1 2
1"
#2290000
0"
#2295000
b10 2
1"
#2300000
0"
#2305000
b11 2
1"
#2310000
0"
#2315000
b10 3
b100000 +
b0 2
1"
#2320000
0"
#2325000
b1 2
1"
#2330000
0"
#2335000
b100 3
b100001 +
b0 2
1"
#2340000
0"
#2345000
b1 2
1"
#2350000
0"
#2355000
b10 2
1"
#2360000
0"
#2365000
b11 2
1"
#2370000
0"
#2375000
b11 3
b100010 +
b0 2
1"
#2380000
0"
#2385000
b1 2
1"
#2390000
0"
#2395000
b10 2
1"
#2400000
0"
#2405000
b100 3
b100011 +
b0 2
1"
#2410000
0"
#2415000
b1 2
1"
#2420000
0"
#2425000
b10 2
1"
#2430000
0"
#2435000
b11 2
1"
#2440000
0"
#2445000
b11 3
b100100 +
b0 2
1"
#2450000
0"
#2455000
b1 2
1"
#2460000
0"
#2465000
b10 2
1"
#2470000
0"
#2475000
b100 3
b100101 +
b0 2
1"
#2480000
0"
#2485000
b1 2
1"
#2490000
0"
#2495000
b10 2
1"
#2500000
0"
#2505000
b11 2
1"
#2510000
0"
#2515000
b100110 +
b0 2
1"
#2520000
0"
#2525000
b1 2
1"
#2530000
0"
#2535000
b10 2
1"
#2540000
0"
#2545000
b11 2
1"
#2550000
0"
#2555000
b100111 +
b0 2
1"
#2560000
0"
#2565000
b1 2
1"
#2570000
0"
#2575000
b10 2
1"
#2580000
0"
#2585000
b11 2
1"
#2590000
0"
#2595000
b101000 +
b0 2
1"
#2600000
0"
#2605000
b1 2
1"
#2610000
0"
#2615000
b10 2
1"
#2620000
0"
#2625000
b11 2
1"
#2630000
0"
#2635000
b10 3
b101001 +
b0 2
1"
#2640000
0"
#2645000
b1 2
1"
#2650000
0"
#2655000
b100 3
b101010 +
b0 2
1"
#2660000
0"
#2665000
b1 2
1"
#2670000
0"
#2675000
b10 2
1"
#2680000
0"
#2685000
b11 2
1"
#2690000
0"
#2695000
b11 3
b101011 +
b0 2
1"
#2700000
0"
#2705000
b1 2
1"
#2710000
0"
#2715000
b10 2
1"
#2720000
0"
#2725000
b1 3
1#
b0 2
1"
#2730000
0"
#2735000
b100 3
b101100 +
0#
b0 2
1"
#2740000
0"
#2745000
b1 2
1"
#2750000
0"
#2755000
b10 2
1"
#2760000
0"
#2765000
b11 2
1"
#2770000
0"
#2775000
b1 3
b101101 +
b0 2
1"
#2780000
0"
#2785000
b10 3
b101110 +
1(
b1001 %
b1001 ,
b0 2
1"
#2790000
0"
#2795000
b1 2
1"
#2800000
0"
#2805000
b100 3
b101111 +
b0 2
1"
#2810000
0"
#2815000
b1 2
1"
#2820000
0"
#2825000
b10 2
1"
#2830000
0"
#2835000
b11 2
1"
#2840000
0"
#2845000
b1 !
b1 .
b11 3
b110000 +
1$
b0 &
b0 -
b0 2
1"
#2850000
0"
#2855000
b10 !
b10 .
b1 2
1"
#2860000
0"
#2865000
b11 !
b11 .
b10 2
1"
#2870000
0"
#2875000
b100 !
b100 .
b110001 +
b0 2
1"
#2880000
0"
#2885000
b101 !
b101 .
b1 2
1"
#2890000
0"
#2895000
b110 !
b110 .
b10 2
1"
#2900000
0"
#2905000
b111 !
b111 .
b10 3
b110010 +
b0 2
1"
#2910000
0"
#2915000
b1000 !
b1000 .
b1 2
1"
#2920000
0"
#2925000
b1001 !
b1001 .
b110011 +
b0 2
1"
#2930000
0"
#2935000
b0 !
b0 .
b1 2
1"
#2940000
0"
#2945000
b1 !
b1 .
b1 3
b110100 +
b0 2
1"
#2950000
0"
#2955000
b10 !
b10 .
b11 3
b110101 +
b0 2
1"
#2960000
0"
#2965000
b11 !
b11 .
b1 2
1"
#2970000
0"
#2975000
b100 !
b100 .
b10 2
1"
#2980000
0"
#2985000
b101 !
b101 .
b110110 +
b0 2
1"
#2990000
0"
#2995000
b110 !
b110 .
b1 2
1"
#3000000
0"
#3005000
b111 !
b111 .
b10 2
1"
#3010000
0"
#3015000
b1000 !
b1000 .
b110111 +
b0 2
1"
#3020000
0"
#3025000
b1001 !
b1001 .
b1 2
1"
#3030000
0"
#3035000
b0 !
b0 .
b10 2
1"
#3040000
0"
#3045000
b1001 !
b1001 .
b111000 +
0(
b0 2
1"
#3050000
0"
#3055000
b1000 !
b1000 .
b1 2
1"
#3060000
0"
#3065000
b111 !
b111 .
b10 2
1"
#3070000
0"
#3075000
b111001 +
0$
b0 2
1"
#3080000
0"
#3085000
b1 2
1"
#3090000
0"
#3095000
b10 2
1"
#3100000
0"
#3105000
b111010 +
b10 %
b10 ,
b0 2
1"
#3110000
0"
#3115000
b1 2
1"
#3120000
0"
#3125000
b10 2
1"
#3130000
0"
#3135000
b111011 +
b110 %
b110 ,
b0 2
1"
#3140000
0"
#3145000
b1 2
1"
#3150000
0"
#3155000
b10 2
1"
#3160000
0"
#3165000
b1 3
b111100 +
b0 2
1"
#3170000
0"
#3175000
b10 3
b111101 +
b0 2
1"
#3180000
0"
#3185000
b1 2
1"
#3190000
0"
#3195000
b100 3
b111110 +
b0 2
1"
#3200000
0"
#3205000
b1 2
1"
#3210000
0"
#3215000
b10 2
1"
#3220000
0"
#3225000
b11 2
1"
#3230000
0"
#3235000
b111111 +
b0 2
1"
#3240000
0"
#3245000
b1 2
1"
#3250000
0"
#3255000
b10 2
1"
#3260000
0"
#3265000
b11 2
1"
#3270000
0"
#3275000
b10 3
b1000000 +
b0 2
1"
#3280000
0"
#3285000
b1 2
1"
#3290000
0"
#3295000
b1 3
b1000001 +
b0 2
1"
#3300000
0"
#3305000
b10 3
b1000010 +
b0 2
1"
#3310000
0"
#3315000
b1 2
1"
#3320000
0"
#3325000
b11 3
b1000011 +
b0 2
1"
#3330000
0"
#3335000
b1 2
1"
#3340000
0"
#3345000
b10 2
1"
#3350000
0"
#3355000
b100 3
b1000100 +
b11 %
b11 ,
b0 2
1"
#3360000
0"
#3365000
b1 2
1"
#3370000
0"
#3375000
b10 2
1"
#3380000
0"
#3385000
b11 2
1"
#3390000
0"
#3395000
b1000101 +
1(
b0 2
1"
#3400000
0"
#3405000
b1 2
1"
#3410000
0"
#3415000
b10 2
1"
#3420000
0"
#3425000
b11 2
1"
#3430000
0"
#3435000
b1000110 +
b0 2
1"
#3440000
0"
#3445000
b1 2
1"
#3450000
0"
#3455000
b10 2
1"
#3460000
0"
#3465000
b11 2
1"
#3470000
0"
#3475000
b1000111 +
b0 2
1"
#3480000
0"
#3485000
b1 2
1"
#3490000
0"
#3495000
b10 2
1"
#3500000
0"
#3505000
b11 2
1"
#3510000
0"
#3515000
b10 3
b1001000 +
b0 2
1"
#3520000
0"
#3525000
b1 2
1"
#3530000
0"
#3535000
b1000 !
b1000 .
b1 3
b1001001 +
1$
b0 2
1"
#3540000
0"
#3545000
b1001 !
b1001 .
b100 3
b1001010 +
b0 2
1"
#3550000
0"
#3555000
b1010 !
b1010 .
b1 2
1"
#3560000
0"
#3565000
b1011 !
b1011 .
b10 2
1"
#3570000
0"
#3575000
b1100 !
b1100 .
b11 2
1"
#3580000
0"
#3585000
b1011 !
b1011 .
b10 3
b1001011 +
0(
b0 2
1"
#3590000
0"
#3595000
b1010 !
b1010 .
b1 2
1"
#3600000
0"
#3605000
b1001 !
b1001 .
b1 3
b1001100 +
b0 2
1"
#3610000
0"
#3615000
b100 3
b1001101 +
0$
b0 2
1"
#3620000
0"
#3625000
b1 2
1"
#3630000
0"
#3635000
b10 2
1"
#3640000
0"
#3645000
b11 2
1"
#3650000
0"
#3655000
b1 3
b1001110 +
b1010 %
b1010 ,
b0 2
1"
#3660000
0"
#3665000
b10 3
b1001111 +
b101 &
b101 -
b0 2
1"
#3670000
0"
#3675000
b1 2
1"
#3680000
0"
#3685000
b1 3
b1010000 +
b0 2
1"
#3690000
0"
#3695000
b100 3
b1010001 +
b0 2
1"
#3700000
0"
#3705000
b1 2
1"
#3710000
0"
#3715000
b10 2
1"
#3720000
0"
#3725000
b11 2
1"
#3730000
0"
#3735000
b1 3
b1010010 +
b1110 %
b1110 ,
b0 2
1"
#3740000
0"
#3745000
b10 3
b1010011 +
b1001 %
b1001 ,
b0 2
1"
#3750000
0"
#3755000
b1 2
1"
#3760000
0"
