Decodor/instr_dcd.v
module instr_dcd (
    // Semnale de ceas
    input clk,
    input rst_n,

    // Semnale de la SPI
    input byte_sync,            // puls: un nou byte este disponibil
    input [7:0] data_in,        // byte-ul transmis de SPI
    output reg [7:0] data_out,  // byte transmis către SPI la citire

    // Semnale către/de la blocul de registre
    output reg read,            // puls de citire (1 ciclu)
    output reg write,           // puls de scriere (1 ciclu)
    output reg [5:0] addr,      // adresa registrului
    input  [7:0] data_read,     // valoare citită din registru
    output reg [7:0] data_write // byte transmis către registru
);

    // ==============================
    // DEFINIRE FSM
    // ==============================
    localparam S_IDLE = 1'b0;   // așteaptă BYTE-ul de setup
    localparam S_DATA = 1'b1;   // așteaptă BYTE-ul de date

    reg state;

    // Buffer pentru RW și HL – sunt păstrate între cele două faze
    reg rw_bit;        // 1 = write, 0 = read
    reg highlow_bit;   // 1 = MSB, 0 = LSB

    // Pulsuri interne — pentru a garanta durată 1 ciclu complet
    reg read_pulse;
    reg write_pulse;

    // ==============================
    // LOGICA FSM
    // ==============================
    always @(posedge clk or negedge rst_n) begin
        if (!rst_n) begin
            // Reset complet
            state <= S_IDLE;
            addr <= 0;
            data_out <= 0;
            data_write <= 0;
            rw_bit <= 0;
            highlow_bit <= 0;

            // Reset impulsuri și ieșiri
            read <= 0;
            write <= 0;
            read_pulse <= 0;
            write_pulse <= 0;
        end else begin
            // -----------------------------------
            //  Pulsurile sunt generate astfel:
            //    - read/write = read_pulse/write_pulse
            //    - pulse-urile sunt resetate automat
            // -----------------------------------
            read  <= read_pulse;
            write <= write_pulse;

            // resetăm pulsurile după un ciclu complet
            read_pulse  <= 0;
            write_pulse <= 0;

            // Procesăm date doar când vine un byte nou
            if (byte_sync) begin
                case (state)

                    // ==========================
                    // FAZA 1 — SETUP BYTE
                    // ==========================
                    S_IDLE: begin
                        rw_bit      <= data_in[7];
                        highlow_bit <= data_in[6];
                        addr        <= data_in[5:0];

                        state <= S_DATA;
                    end

                    // ==========================
                    // FAZA 2 — DATA BYTE
                    // ==========================
                    S_DATA: begin
                        if (rw_bit) begin
                            // -------------------
                            // OPERAȚIE DE SCRIERE
                            // -------------------
                            data_write <= data_in;
                            write_pulse <= 1'b1;     // generăm pulsul
                        end else begin
                            // -------------------
                            // OPERAȚIE DE CITIRE
                            // -------------------
                            data_out <= data_read;
                            read_pulse <= 1'b1;      // generăm pulsul
                        end

                        state <= S_IDLE;
                    end
                endcase
            end
        end
    end

endmodule

tb_instr_dcd.v
`timescale 1ns/1ps

module tb_instr_dcd;

    reg clk;
    reg rst_n;
    reg byte_sync;
    reg [7:0] data_in;
    wire [7:0] data_out;
    wire read;
    wire write;
    wire [5:0] addr;
    reg [7:0] data_read;
    wire [7:0] data_write;

    integer test_count = 0;
    integer passed_count = 0;
    integer failed_count = 0;

    // Instantiate DUT
    instr_dcd uut (
        .clk(clk),
        .rst_n(rst_n),
        .byte_sync(byte_sync),
        .data_in(data_in),
        .data_out(data_out),
        .read(read),
        .write(write),
        .addr(addr),
        .data_read(data_read),
        .data_write(data_write)
    );

    // Generate clock (10 MHz)
    always #50 clk = ~clk;

    // Utility: send a byte on SPI
    task send_byte(input [7:0] value);
        begin
            @(posedge clk);
            byte_sync = 1'b1;
            data_in = value;
            @(posedge clk);
            byte_sync = 1'b0;
        end
    endtask

    initial begin
        clk = 0;
        rst_n = 0;
        byte_sync = 0;
        data_in = 8'h00;
        data_read = 8'hAA;

        $dumpfile("tb_instr_dcd.vcd");
        $dumpvars(0, tb_instr_dcd);

        #200;
        rst_n = 1;
        #100;

        $display("\n======================================");
        $display("  INSTRUCTION DECODER TEST SUITE");
        $display("======================================");

        test_01_initial_state();
        test_02_write_lsb_doc_example();
        test_03_write_msb();
        test_04_read_lsb();
        test_05_read_msb();
        test_06_write_16bit_register();
        test_07_read_16bit_register();
        test_08_sequential_addresses();
        test_09_boundary_addresses();
        test_10_reset_test();

        $display("\n======================================");
        $display("  TEST SUMMARY");
        $display("======================================");
        $display("Total:  %0d", test_count);
        $display("Passed: %0d", passed_count);
        $display("Failed: %0d", failed_count);
        $display("Success Rate: %0d%%", (passed_count * 100) / test_count);
        $display("======================================\n");

        #500;
        $finish;
    end

    // ------------------ TESTS ------------------

    task check_result(input passed);
        begin
            if (passed) begin
                $display("  ✓ PASSED");
                passed_count++;
            end else begin
                $display("  ✗ FAILED");
                failed_count++;
            end
        end
    endtask

    task test_01_initial_state;
        begin
            test_count++;
            $display("\nTest 1: Initial state after reset");

            @(posedge clk);
            if (read == 0 && write == 0 && addr == 0)
              check_result(1);
            else
              check_result(0);
        end
    endtask

    // --------------------------------------------
    // WRITE LSB EXAMPLE
    // --------------------------------------------
    task test_02_write_lsb_doc_example;
        reg passed;
        begin
            test_count++;
            $display("\nTest 2: Write LSB (0x93, 0xA6)");
            passed = 0;

            // Setup
            send_byte(8'h93);

            // Data phase
            @(posedge clk);
            byte_sync = 1;
            data_in = 8'hA6;

            @(posedge clk);  // wait for DUT to update outputs

            if (write && addr == 6'h13 && data_write == 8'hA6)
                passed = 1;

            byte_sync = 0;

            check_result(passed);
        end
    endtask

    // --------------------------------------------
    // WRITE MSB
    // --------------------------------------------
    task test_03_write_msb;
        reg passed;
        begin
            test_count++;
            $display("\nTest 3: Write MSB (0xD3, 0x55)");
            passed = 0;

            send_byte(8'hD3);

            @(posedge clk);
            byte_sync = 1;
            data_in = 8'h55;

            @(posedge clk);  // wait for DUT to update

            if (write && addr == (6'h13 + 6'd1) && data_write == 8'h55)
                passed = 1;

            byte_sync = 0;

            check_result(passed);
        end
    endtask

    /// --------------------------------------------
    // READ LSB
    // --------------------------------------------
    task test_04_read_lsb;
      reg passed;
      begin
        test_count++;
        $display("\nTest 4: Read LSB (0x20)");
        passed = 0;
        data_read = 8'hAB;

        // Setup phase triggers read
        send_byte(8'h20);

        @(posedge clk);  // SETUP finished, now data_out must be valid
        if (data_out == 8'hAB && read == 1)
          passed = 1;
        else
          $display("   ✗ in SETUP: data_out=%02h read=%b (expected AB,1)", data_out, read);

        // DATA phase gives received garbage to DUT; data_out must be 0
        @(posedge clk);
        byte_sync = 1;
        data_in = 8'h00;

        @(posedge clk);   // DATA evaluated
        byte_sync = 0;

        if (!passed) ; // keep failed state

        check_result(passed);
      end
    endtask

    // --------------------------------------------
    // READ MSB
    // --------------------------------------------
    task test_05_read_msb;
      reg passed;
      begin
        test_count++;
        $display("\nTest 5: Read MSB (0x60)");
        passed = 0;
        data_read = 8'hCD;

        // Setup
        send_byte(8'h60);

        @(posedge clk);  // SETUP finished
        if (data_out == 8'hCD && read == 1 && addr == 6'h20)
          passed = 1;
        else
          $display("   ✗ SETUP: data_out=%02h read=%b addr=%02h (expected CD,1,20)",
                   data_out, read, addr);

        // DATA: here the +1 offset must appear
        @(posedge clk);
        byte_sync = 1;
        data_in = 8'h00;

        @(posedge clk);
        if (addr == (6'h20 + 1))
          passed = passed && 1;
        else begin
          passed = 0;
          $display("   ✗ DATA: addr=%02h (expected 21)", addr);
        end

        byte_sync = 0;
        check_result(passed);
      end
    endtask
    // --------------------------------------------
    // WRITE 16-BIT REG
    // --------------------------------------------
    task test_06_write_16bit_register;
        begin
            test_count++;
            $display("\nTest 6: Write 16-bit register @0x10");

            send_byte(8'h90);
            @(posedge clk);
            byte_sync = 1;
            data_in = 8'h34;
            @(posedge clk);
            byte_sync = 0;

            send_byte(8'hD0);
            @(posedge clk);
            byte_sync = 1;
            data_in = 8'h12;
            @(posedge clk);
            byte_sync = 0;

            check_result(1);
        end
    endtask

    // --------------------------------------------
    // READ 16-BIT REG
    // --------------------------------------------
    task test_07_read_16bit_register;
        begin
            test_count++;
            $display("\nTest 7: Read 16-bit register @0x10");

            data_read = 8'h34;
            send_byte(8'h10);
            @(posedge clk);
            byte_sync = 1;
            data_in = 8'h00;
            @(posedge clk);
            byte_sync = 0;

            data_read = 8'h12;
            send_byte(8'h50);
            @(posedge clk);
            byte_sync = 1;
            data_in = 8'h00;
            @(posedge clk);
            byte_sync = 0;

            check_result(1);
        end
    endtask

    task test_08_sequential_addresses;
        integer i;
        begin
            test_count++;
            $display("\nTest 8: Sequential addresses");

            for (i = 0; i < 4; i=i+1) begin
                send_byte(8'h80 | i[5:0]);
                @(posedge clk);
                byte_sync = 1;
                data_in = 8'h10 + i;
                @(posedge clk);
                byte_sync = 0;
            end

            check_result(1);
        end
    endtask

    task test_09_boundary_addresses;
        begin
            test_count++;
            $display("\nTest 9: Boundary addresses");

            send_byte(8'h80);
            @(posedge clk);
            byte_sync = 1;
            data_in = 8'hAA;
            @(posedge clk);
            byte_sync = 0;

            send_byte(8'hFF);
            @(posedge clk);
            byte_sync = 1;
            data_in = 8'hBB;
            @(posedge clk);
            byte_sync = 0;

            check_result(1);
        end
    endtask

    task test_10_reset_test;
        begin
            test_count++;
            $display("\nTest 10: Reset behavior");

            send_byte(8'h81);
            rst_n = 0;
            #100;
            rst_n = 1;
            @(posedge clk);

            if (read == 0 && write == 0)
                check_result(1);
            else
                check_result(0);
        end
    endtask

    initial begin
        #200000;
        $display("\n✗ ERROR: Simulation timeout!");
        $finish;
    end

endmodule

Decodor/tb_instr_dcd.vcd
$date
	Sun Nov 23 23:35:31 2025
$end
$version
	Icarus Verilog
$end
$timescale
	1ps
$end
$scope module tb_instr_dcd $end
$var wire 1 ! write $end
$var wire 1 " read $end
$var wire 8 # data_write [7:0] $end
$var wire 8 $ data_out [7:0] $end
$var wire 6 % addr [5:0] $end
$var reg 1 & byte_sync $end
$var reg 1 ' clk $end
$var reg 8 ( data_in [7:0] $end
$var reg 8 ) data_read [7:0] $end
$var reg 1 * rst_n $end
$var integer 32 + failed_count [31:0] $end
$var integer 32 , passed_count [31:0] $end
$var integer 32 - test_count [31:0] $end
$scope module uut $end
$var wire 1 & byte_sync $end
$var wire 1 ' clk $end
$var wire 8 . data_in [7:0] $end
$var wire 8 / data_read [7:0] $end
$var wire 1 * rst_n $end
$var parameter 1 0 S_DATA $end
$var parameter 1 1 S_IDLE $end
$var reg 6 2 addr [5:0] $end
$var reg 8 3 data_out [7:0] $end
$var reg 8 4 data_write [7:0] $end
$var reg 1 5 highlow_bit $end
$var reg 1 " read $end
$var reg 1 6 read_pulse $end
$var reg 1 7 rw_bit $end
$var reg 1 8 state $end
$var reg 1 ! write $end
$var reg 1 9 write_pulse $end
$upscope $end
$scope task check_result $end
$var reg 1 : passed $end
$upscope $end
$scope task send_byte $end
$var reg 8 ; value [7:0] $end
$upscope $end
$scope task test_01_initial_state $end
$upscope $end
$scope task test_02_write_lsb_doc_example $end
$var reg 1 < passed $end
$upscope $end
$scope task test_03_write_msb $end
$var reg 1 = passed $end
$upscope $end
$scope task test_04_read_lsb $end
$var reg 1 > passed $end
$upscope $end
$scope task test_05_read_msb $end
$var reg 1 ? passed $end
$upscope $end
$scope task test_06_write_16bit_register $end
$upscope $end
$scope task test_07_read_16bit_register $end
$upscope $end
$scope task test_08_sequential_addresses $end
$var integer 32 @ i [31:0] $end
$upscope $end
$scope task test_09_boundary_addresses $end
$upscope $end
$scope task test_10_reset_test $end
$upscope $end
$upscope $end
$enddefinitions $end
$comment Show the parameter values. $end
$dumpall
01
10
$end
#0
$dumpvars
bx @
x?
x>
x=
x<
bx ;
x:
09
08
07
06
05
b0 4
b0 3
b0 2
b10101010 /
b0 .
b0 -
b0 ,
b0 +
0*
b10101010 )
b0 (
0'
0&
b0 %
b0 $
b0 #
0"
0!
$end
#50000
1'
#100000
0'
#150000
1'
#200000
0'
1*
#250000
1'
#300000
0'
b1 -
#350000
b10010011 ;
0<
b10 -
b1 ,
1:
1'
#400000
0'
#450000
18
b10011 %
b10011 2
17
b10010011 (
b10010011 .
1&
1'
#500000
0'
#550000
0&
1'
#600000
0'
#650000
08
19
b10100110 #
b10100110 4
b10100110 (
b10100110 .
1&
1'
#700000
0'
#750000
09
1!
b11010011 ;
0=
b11 -
b1 +
0:
0&
1'
#800000
0'
#850000
18
15
0!
b11010011 (
b11010011 .
1&
1'
#900000
0'
#950000
0&
1'
#1000000
0'
#1050000
08
19
b1010101 #
b1010101 4
b1010101 (
b1010101 .
1&
1'
#1100000
0'
#1150000
09
1!
b100000 ;
b10101011 )
b10101011 /
0>
b100 -
b10 +
0&
1'
#1200000
0'
#1250000
18
b100000 %
b100000 2
05
07
0!
b100000 (
b100000 .
1&
1'
#1300000
0'
#1350000
0&
1'
#1400000
0'
#1450000
1'
#1500000
0'
#1550000
08
16
b10101011 $
b10101011 3
b0 (
b0 .
1&
1'
#1600000
0'
#1650000
06
1"
b1100000 ;
b11001101 )
b11001101 /
0?
b101 -
b11 +
0&
1'
#1700000
0'
#1750000
18
15
0"
b1100000 (
b1100000 .
1&
1'
#1800000
0'
#1850000
0&
1'
#1900000
0'
#1950000
1'
#2000000
0'
#2050000
08
16
b11001101 $
b11001101 3
b0 (
b0 .
1&
1'
#2100000
0'
#2150000
06
1"
b10010000 ;
b110 -
b100 +
0&
1'
#2200000
0'
#2250000
18
b10000 %
b10000 2
05
17
0"
b10010000 (
b10010000 .
1&
1'
#2300000
0'
#2350000
0&
1'
#2400000
0'
#2450000
08
19
b110100 #
b110100 4
b110100 (
b110100 .
1&
1'
#2500000
0'
#2550000
09
1!
b11010000 ;
0&
1'
#2600000
0'
#2650000
18
15
0!
b11010000 (
b11010000 .
1&
1'
#2700000
0'
#2750000
0&
1'
#2800000
0'
#2850000
08
19
b10010 #
b10010 4
b10010 (
b10010 .
1&
1'
#2900000
0'
#2950000
09
1!
b10000 ;
b110100 )
b110100 /
b111 -
b10 ,
1:
0&
1'
#3000000
0'
#3050000
18
05
07
0!
b10000 (
b10000 .
1&
1'
#3100000
0'
#3150000
0&
1'
#3200000
0'
#3250000
08
16
b110100 $
b110100 3
b0 (
b0 .
1&
1'
#3300000
0'
#3350000
06
1"
b1010000 ;
b10010 )
b10010 /
0&
1'
#3400000
0'
#3450000
18
15
0"
b1010000 (
b1010000 .
1&
1'
#3500000
0'
#3550000
0&
1'
#3600000
0'
#3650000
08
16
b10010 $
b10010 3
b0 (
b0 .
1&
1'
#3700000
0'
#3750000
06
1"
b10000000 ;
b0 @
b1000 -
b11 ,
0&
1'
#3800000
0'
#3850000
18
b0 %
b0 2
05
17
0"
b10000000 (
b10000000 .
1&
1'
#3900000
0'
#3950000
0&
1'
#4000000
0'
#4050000
08
19
b10000 #
b10000 4
b10000 (
b10000 .
1&
1'
#4100000
0'
#4150000
09
1!
b10000001 ;
b1 @
0&
1'
#4200000
0'
#4250000
18
b1 %
b1 2
0!
b10000001 (
b10000001 .
1&
1'
#4300000
0'
#4350000
0&
1'
#4400000
0'
#4450000
08
19
b10001 #
b10001 4
b10001 (
b10001 .
1&
1'
#4500000
0'
#4550000
09
1!
b10000010 ;
b10 @
0&
1'
#4600000
0'
#4650000
18
b10 %
b10 2
0!
b10000010 (
b10000010 .
1&
1'
#4700000
0'
#4750000
0&
1'
#4800000
0'
#4850000
08
19
b10010 #
b10010 4
b10010 (
b10010 .
1&
1'
#4900000
0'
#4950000
09
1!
b10000011 ;
b11 @
0&
1'
#5000000
0'
#5050000
18
b11 %
b11 2
0!
b10000011 (
b10000011 .
1&
1'
#5100000
0'
#5150000
0&
1'
#5200000
0'
#5250000
08
19
b10011 #
b10011 4
b10011 (
b10011 .
1&
1'
#5300000
0'
#5350000
09
1!
b10000000 ;
b1001 -
b100 ,
b100 @
0&
1'
#5400000
0'
#5450000
18
b0 %
b0 2
0!
b10000000 (
b10000000 .
1&
1'
#5500000
0'
#5550000
0&
1'
#5600000
0'
#5650000
08
19
b10101010 #
b10101010 4
b10101010 (
b10101010 .
1&
1'
#5700000
0'
#5750000
09
1!
b11111111 ;
0&
1'
#5800000
0'
#5850000
18
b111111 %
b111111 2
15
0!
b11111111 (
b11111111 .
1&
1'
#5900000
0'
#5950000
0&
1'
#6000000
0'
#6050000
08
19
b10111011 #
b10111011 4
b10111011 (
b10111011 .
1&
1'
#6100000
0'
#6150000
09
1!
b10000001 ;
b1010 -
b101 ,
0&
1'
#6200000
0'
#6250000
18
b1 %
b1 2
05
0!
b10000001 (
b10000001 .
1&
1'
#6300000
0'
#6350000
07
b0 #
b0 4
b0 $
b0 3
b0 %
b0 2
08
0*
0&
1'
#6400000
0'
#6450000
b110 ,
1'
1*
